Workbook

Sheet Main Page
A1: r
E2: TEST CASES
B5: Project Title | D5: Sta Rosa Payment Portal Phase 2 | H5: Project Manager | I5: Justin Orolfo
B6: Project Start Date | E6: Project End Date | H6: Project Client | I6: SMSGT
B8: Introduction
B9: This document outlines a set of test cases for Phase 2 of the City Government of Santa Rosa's Online Payment Portal. These test cases are derived from the Business Requirements Document (BRD) and Functional Requirements Document (FRD) and aim to verify that the new functionalities for the City Health Office (CHO I and II) and the Assessor’s Office meet the specified requirements and perform as expected
B11: Test Case Structure
B12: Each test case will follow the structure below:
B13: Test Case ID | G13: Unique identifier for the test case (e.g., TC-UI-001).
B14: Test Objective | G14: A clear statement of what is being tested.
B15: Preconditions | G15: Any prerequisites that must be met before executing the test case.
B16: Test Steps | G16: A detailed, step-by-step procedure to execute the test.
B17: Expected Result | G17: The anticipated outcome if the system is functioning correctly.
B18: Status | G18: (To be filled during testing: Pass/Fail/Blocked/N/A)
B19: Comments | G19: (Any relevant notes or observations during testing)

Sheet Dashboard
A3: Total Outstanding | B3: Status | C3: TOTAL | D3: PG-US-01 | E3: PG-US-02 | F3: PG-US-03 | G3: PG-US-04 | H3: PG-US-05 | I3: PG-US-06 | J3: PG-US-07 | K3: PG-US-08 | L3: PG-US-09 | M3: PG-US-10 | N3: PG-US-11 | O3: PG-US-12 | P3: PG-US-13 | Q3: PG-US-14 | R3: PG-US-15 | S3: PG-US-16 | T3: PG-US-17 | U3: AO-US-01 | V3: AO-US-02 | W3: AO-US-03
A4: =Sum(D4:T6) -> 404 | B4: OPEN | C4: =SUM(D4:T4) -> 366 | D4: =COUNTIF('PG-US-01'!F:F, "OPEN") -> 0 | E4: =COUNTIF('PG-US-02'!F:F, "OPEN") -> 0 | F4: =COUNTIF('PG-US-03'!F:F, "OPEN") -> 0 | G4: =COUNTIF('PG-US-04'!F:F, "OPEN") -> 0 | H4: =COUNTIF('PG-US-05'!F:F, "OPEN") -> 19 | I4: =COUNTIF('PG-US-06'!F:F, "OPEN") -> 16 | J4: =COUNTIF('PG-US-07'!F:F, "OPEN") -> 16 | K4: =COUNTIF('PG-US-08'!F:F, "OPEN") -> 16 | L4: =COUNTIF('PG-US-09'!F:F, "OPEN") -> 16 | M4: =COUNTIF('PG-US-10'!F:F, "OPEN") -> 0 | N4: =COUNTIF('PG-US-11'!F:F, "OPEN") -> 9 | O4: =COUNTIF('PG-US-12'!F:F, "OPEN") -> 63 | P4: =COUNTIF('PG-US-13'!F:F, "OPEN") -> 72 | Q4: =COUNTIF('PG-US-14'!F:F, "OPEN") -> 55 | R4: =COUNTIF('PG-US-15'!F:F, "OPEN") -> 13 | S4: =COUNTIF('PG-US-16'!F:F, "OPEN") -> 3 | T4: =COUNTIF('PG-US-17'!$F:$F, "OPEN") -> 68 | U4: =COUNTIF('AO-US-01'!$F:$F, "OPEN") -> 3 | V4: =COUNTIF('AO-US-02'!$F:$F, "OPEN") -> 105 | W4: =COUNTIF('AO-US-03'!$F:$F, "OPEN") -> 22
B5: FAILED | C5: =SUM(D5:T5) -> 37 | D5: =COUNTIF('PG-US-01'!F:F, "FAILED") -> 5 | E5: =COUNTIF('PG-US-02'!F:F, "FAILED") -> 2 | F5: =COUNTIF('PG-US-03'!F:F, "FAILED") -> 0 | G5: =COUNTIF('PG-US-04'!F:F, "FAILED") -> 0 | H5: =COUNTIF('PG-US-05'!F:F, "FAILED") -> 1 | I5: =COUNTIF('PG-US-06'!F:F, "FAILED") -> 1 | J5: =COUNTIF('PG-US-07'!F:F, "FAILED") -> 2 | K5: =COUNTIF('PG-US-08'!F:F, "FAILED") -> 2 | L5: =COUNTIF('PG-US-09'!F:F, "FAILED") -> 2 | M5: =COUNTIF('PG-US-10'!F:F, "FAILED") -> 14 | N5: =COUNTIF('PG-US-11'!F:F, "FAILED") -> 7 | O5: =COUNTIF('PG-US-12'!F:F, "FAILED") -> 0 | P5: =COUNTIF('PG-US-13'!F:F, "FAILED") -> 0 | Q5: =COUNTIF('PG-US-14'!F:F, "FAILED") -> 0 | R5: =COUNTIF('PG-US-15'!F:F, "FAILED") -> 1 | S5: =COUNTIF('PG-US-16'!F:F, "FAILED") -> 0 | T5: =COUNTIF('PG-US-17'!$F:$F, "FAILED") -> 0 | U5: =COUNTIF('AO-US-01'!$F:$F, "FAILED") -> 1 | V5: =COUNTIF('AO-US-02'!$F:$F, "FAILED") -> 17 | W5: =COUNTIF('AO-US-03'!$F:$F, "FAILED") -> 1
B6: BLOCKED | C6: =SUM(D6:T6) -> 1 | D6: =COUNTIF('PG-US-01'!F:F, "BLOCKED") -> 0 | E6: =COUNTIF('PG-US-02'!F:F, "BLOCKED") -> 1 | F6: =COUNTIF('PG-US-03'!F:F, "BLOCKED") -> 0 | G6: =COUNTIF('PG-US-04'!F:F, "BLOCKED") -> 0 | H6: =COUNTIF('PG-US-05'!F:F, "BLOCKED") -> 0 | I6: =COUNTIF('PG-US-06'!F:F, "BLOCKED") -> 0 | J6: =COUNTIF('PG-US-07'!F:F, "BLOCKED") -> 0 | K6: =COUNTIF('PG-US-08'!F:F, "BLOCKED") -> 0 | L6: =COUNTIF('PG-US-09'!F:F, "BLOCKED") -> 0 | M6: =COUNTIF('PG-US-10'!F:F, "BLOCKED") -> 0 | N6: =COUNTIF('PG-US-11'!F:F, "BLOCKED") -> 0 | O6: =COUNTIF('PG-US-12'!F:F, "BLOCKED") -> 0 | P6: =COUNTIF('PG-US-13'!F:F, "BLOCKED") -> 0 | Q6: =COUNTIF('PG-US-14'!F:F, "BLOCKED") -> 0 | R6: =COUNTIF('PG-US-15'!F:F, "BLOCKED") -> 0 | S6: =COUNTIF('PG-US-16'!F:F, "BLOCKED") -> 0 | T6: =COUNTIF('PG-US-17'!$F:$F, "BLOCKED") -> 0 | U6: =COUNTIF('AO-US-01'!$F:$F, "BLOCKED") -> 0 | V6: =COUNTIF('AO-US-02'!$F:$F, "BLOCKED") -> 0 | W6: =COUNTIF('AO-US-03'!$F:$F, "BLOCKED") -> 0
B7: PASSED | C7: =SUM(D7:T7) -> 378 | D7: =COUNTIF('PG-US-01'!F:F, "PASSED") -> 10 | E7: =COUNTIF('PG-US-02'!F:F, "PASSED") -> 12 | F7: =COUNTIF('PG-US-03'!F:F, "PASSED") -> 7 | G7: =COUNTIF('PG-US-04'!F:F, "PASSED") -> 9 | H7: =COUNTIF('PG-US-05'!F:F, "PASSED") -> 39 | I7: =COUNTIF('PG-US-06'!F:F, "PASSED") -> 44 | J7: =COUNTIF('PG-US-07'!F:F, "PASSED") -> 51 | K7: =COUNTIF('PG-US-08'!F:F, "PASSED") -> 59 | L7: =COUNTIF('PG-US-09'!F:F, "PASSED") -> 30 | M7: =COUNTIF('PG-US-10'!F:F, "PASSED") -> 47 | N7: =COUNTIF('PG-US-11'!F:F, "PASSED") -> 48 | O7: =COUNTIF('PG-US-12'!F:F, "PASSED") -> 0 | P7: =COUNTIF('PG-US-13'!F:F, "PASSED") -> 0 | Q7: =COUNTIF('PG-US-14'!F:F, "PASSED") -> 16 | R7: =COUNTIF('PG-US-15'!F:F, "PASSED") -> 5 | S7: =COUNTIF('PG-US-16'!F:F, "PASSED") -> 1 | T7: =COUNTIF('PG-US-17'!$F:$F, "PASSED") -> 0 | U7: =COUNTIF('AO-US-01'!$F:$F, "PASSED") -> 82 | V7: =COUNTIF('AO-US-02'!$F:$F, "PASSED") -> 49 | W7: =COUNTIF('AO-US-03'!$F:$F, "PASSED") -> 6
C9: ='PG-US-01'!$A$1 -> PG-US-01 | E9: ='PG-US-02'!$A$1 -> PG-US-02 | G9: ='PG-US-03'!$A$1 -> PG-US-03 | I9: ='PG-US-04'!$A$1 -> PG-US-04 | K9: ='PG-US-05'!$A$1 -> PG-US-05 | M9: ='PG-US-06'!$A$1 -> PG-US-06 | O9: ='PG-US-07'!$A$1 -> PG-US-07 | Q9: ='PG-US-08'!$A$1 -> PG-US-08 | S9: ='PG-US-09'!$A$1 -> PG-US-09 | U9: ='PG-US-10'!$A$1 -> PG-US-10 | W9: ='PG-US-11'!$A$1 -> PG-US-11 | Y9: ='PG-US-12'!$A$1 -> PG-US-12 | AA9: ='PG-US-13'!$A$1 -> PG-US-13 | AC9: ='PG-US-14'!$A$1 -> PG-US-14 | AE9: ='PG-US-15'!$A$1 -> PG-US-15 | AG9: ='PG-US-16'!$A$1 -> PG-US-16 | AI9: ='PG-US-17'!$A$1 -> PG-US-17 | AK9: ='AO-US-01'!$A$1 -> AO-US-01 | AM9: ='AO-US-02'!$A$1 -> AO-US-01 | AO9: ='AO-US-02'!$A$1 -> AO-US-01
A10: PROGRESS TRACKER | C10: ='PG-US-01'!B1 -> USER STORY: As a new user, I want to click the 'New? Sign Up' button on the login page so that I can access the registration form and create an account. | E10: ='PG-US-02'!B1 -> USER STORY: As a registered user of the Assessor’s Office portal, I want to log in using my email and password, So that I can access my personal records and services provided by the City of Sta. Rosa. | G10: ='PG-US-03'!B1 -> USER STORY: As a new user of the Assessor’s Office portal, I want to see a confirmation message after submitting my email for verification, So that I know the next steps and can return to the homepage easily. | I10: ='PG-US-04'!B1 -> USER STORY: As a logged-in user of the Assessor’s Office portal, I want to access my profile, logout option, see a welcome message, and submit new requests easily, So that I can efficiently manage my account and services. | K10: ='PG-US-05'!B1 -> USER STORY: As a property owner, I want to apply for a Certificate of True Copy of Tax Declaration So that I can process my property documentation And have it claimed as Personal | M10: ='PG-US-06'!B1 -> USER STORY: As a property owner, I want to apply for a Certificate of True Copy of Tax Declaration So that I can process my property documentation And have it claimed by an Authorized Representative on my behalf. | O10: ='PG-US-07'!B1 -> USER STORY: As a property owner, I want to apply for a Transfer of Tax Declaration So that I can process my property documentation And claim the certificate in Personal. | Q10: ='PG-US-08'!B1 -> USER STORY: As a property owner, I want to apply for a Transfer of Tax So that I can process my property documentation And claim the certificate by an Authorized Representative. | S10: ='PG-US-09'!B1 -> USER STORY: As a property owner, I want to apply for a Certificate of No-Property So that I can process my property documentation And claim the certificate in Personal. | U10: ='PG-US-10'!B1 -> USER STORY: As a property owner, I want to apply for a Certificate of No-Property So that I can process my property documentation And have it claimed by an Authorized Representative on my behalf. | W10: ='PG-US-11'!B1 -> USER STORY: As a property owner, I want to apply for a Certificate of Aggregate Landholdings So that I can process my property documentation And claim the certificate in Personal. | Y10: ='PG-US-12'!B1 -> USER STORY: As a property owner, I want to apply for a Certificate of Aggregate Landholdings So that I can process my property documentation And have it claimed by an Authorized Representative on my behalf. | AA10: ='PG-US-13'!B1 -> USER STORY: As a property owner, I want to apply for a Others Documents So that I can process my property documentation And claim the certificate in Personal. | AC10: ='PG-US-14'!B1 -> USER STORY: As a property owner, I want to apply for a Other Documents So that I can process my property documentation And have it claimed by an Authorized Representative on my behalf. | AE10: ='PG-US-15'!B1 -> USER STORY: DASHBOARD As a registered user, I want to view the list of my ongoing certificate applications with details like Ticket ID, status, amount, date, and upload/payment options, so that I can monitor the progress, fulfill missing requirements, make payments if applicable, and ensure my applications are processed smoothly. | AG10: ='PG-US-16'!B1 -> USER STORY: DASHBOARD As a registered user, I want to view my past certificate claims (History) with Ticket IDs, dates, and the list of claimed certificates using a year filter and search, so that I can access a full record of my completed applications for future reference or documentation. | AI10: ='PG-US-17'!B1 -> USER STORY: As a property owner, I want to apply for both the Certificate of True Copy of Tax Declaration and Transfer of Tax Declaration So that I can process my property documentation And claim it personally. | AK10: ='AO-US-01'!B1 -> USER STORY: As a system admistrator, I want to configure and edit email templates based on request status, So that the system can automatically send appropriate and customizable notifications to users at each stage of their certificate request. | AM10: ='AO-US-02'!B1 -> USER STORY: As a system administrator, I want to view, filter, and manage certificate requests submitted by applicants, So that I can monitor the status of each request, update records, and take appropriate actions such as editing or deleting submissions. | AO10: ='AO-US-03'!B1 -> USER STORY: As a system administrator, I want to configure and manage email notifications assigned to specific internal user groups and status types, So that the correct group (e.g., AO Officer, Treasury Office, BPLO Admin) receives automated updates or task reminders as certificate requests move through different statuses.
C11: Status | D11: Comment | E11: Status | F11: Comment | G11: Status | H11: Comment | I11: Status | J11: Comment | K11: Status | L11: Comment | M11: Status | N11: Comment | O11: Status | P11: Comment | Q11: Status | R11: Comment | S11: Status | T11: Comment | U11: Status | V11: Comment | W11: Status | X11: Comment | Y11: Status | Z11: Comment | AA11: Status | AB11: Comment | AC11: Status | AD11: Comment | AE11: Status | AF11: Comment | AG11: Status | AH11: Comment | AI11: Status | AJ11: Comment | AK11: Status | AL11: Comment | AM11: Status | AN11: Comment | AO11: Status | AP11: Comment
A12: US-TC-01 | C12: {='PG-US-01'!F3:F994} -> PASSED | D12: {='PG-US-01'!G3:G994} | E12: {='PG-US-02'!F3:F994} -> PASSED | F12: {='PG-US-02'!G3:G994} | G12: {='PG-US-03'!F3:F994} -> PASSED | H12: {='PG-US-03'!G3:G994} | I12: {='PG-US-04'!F3:F994} -> PASSED | J12: {='PG-US-04'!G3:G994} -> "type of certificate" field changed to drop down. comma text no longer applicable. multi select from drop down doesnt seem to be allowed but primary function working | K12: {='PG-US-05'!F3:F994} -> PASSED | L12: {='PG-US-05'!G3:G994} | M12: {='PG-US-06'!F3:F994} -> PASSED | N12: {='PG-US-06'!G3:G994} | O12: {='PG-US-07'!F3:F994} -> PASSED | P12: {='PG-US-07'!G3:G994} | Q12: {='PG-US-08'!F3:F994} -> PASSED | R12: {='PG-US-08'!G3:G994} | S12: {='PG-US-09'!F3:F994} -> PASSED | T12: {='PG-US-09'!G3:G994} | U12: {='PG-US-10'!F3:F994} -> PASSED | V12: {='PG-US-10'!G3:G994} | W12: {='PG-US-11'!F3:F994} -> PASSED | X12: {='PG-US-11'!G3:G994} | Y12: {='PG-US-12'!F3:F994} -> OPEN | Z12: {='PG-US-12'!G3:G994} | AA12: {='PG-US-13'!F3:F994} -> OPEN | AB12: {='PG-US-13'!G3:G994} | AC12: {='PG-US-14'!F3:F994} -> PASSED | AD12: {='PG-US-14'!G3:G994} | AE12: {='PG-US-15'!F3:F994} -> PASSED | AF12: {='PG-US-15'!G3:G994} | AG12: {='PG-US-16'!F3:F994} -> OPEN | AH12: {='PG-US-16'!G3:G994} | AI12: {='PG-US-17'!$F$3:$F994} -> OPEN | AJ12: {='PG-US-17'!$G$3:$G994} | AK12: {='AO-US-01'!$F$3:$F994} -> PASSED | AL12: {='AO-US-01'!$G$3:$G994} | AM12: {='AO-US-02'!$F$3:$F994} -> PASSED | AN12: {='AO-US-02'!$G$3:$G994} | AO12: {='AO-US-03'!$F$3:$F994} -> FAILED | AP12: {='AO-US-03'!$G$3:$G994} -> working - however there is no validation if the exact group and status is submitted as an already existing record
A13: US-TC-02 | C13: FAILED | D13: It accepts contact numbers that start with '09', but it also accepts inputs even if all the characters are not numeric. | E13: PASSED | G13: PASSED | I13: PASSED | K13: PASSED | M13: PASSED | O13: PASSED | Q13: PASSED | S13: PASSED | U13: PASSED | W13: PASSED | Y13: OPEN | AA13: OPEN | AC13: PASSED | AE13: PASSED | AG13: OPEN | AI13: OPEN | AK13: PASSED | AM13: PASSED | AN13: suggestion to match ticket ID with user portal's ticket ID | AO13: PASSED
A14: US-TC-03 | C14: FAILED | D14: It accepts contact numbers that start with '639', but it also accepts inputs even if all the characters are not numeric. | E14: PASSED | G14: PASSED | I14: PASSED | K14: PASSED | M14: PASSED | O14: PASSED | Q14: PASSED | S14: PASSED | U14: PASSED | W14: PASSED | Y14: OPEN | AA14: OPEN | AC14: PASSED | AE14: PASSED | AG14: OPEN | AH14: works and displays "No data available in table" but if there is no data to be shown, does the year filter drop down become disabled/unclickable? if the drop down only visible IF there's records in the history database? | AI14: OPEN | AK14: PASSED | AM14: PASSED | AO14: PASSED
A15: US-TC-04 | C15: PASSED | E15: PASSED | G15: PASSED | I15: PASSED | K15: PASSED | M15: PASSED | O15: PASSED | Q15: PASSED | S15: PASSED | U15: PASSED | W15: PASSED | Y15: OPEN | AA15: OPEN | AC15: PASSED | AE15: PASSED | AG15: PASSED | AI15: OPEN | AK15: PASSED | AM15: PASSED | AO15: PASSED
A16: US-TC-05 | C16: PASSED | E16: PASSED | G16: PASSED | I16: PASSED | K16: PASSED | M16: PASSED | O16: PASSED | Q16: PASSED | S16: PASSED | U16: PASSED | W16: PASSED | Y16: OPEN | AA16: OPEN | AC16: PASSED | AE16: PASSED | AI16: OPEN | AK16: PASSED | AM16: PASSED | AO16: PASSED
A17: US-TC-06 | C17: PASSED | E17: FAILED | F17: triggers T&C validation but button does not disable | G17: PASSED | I17: PASSED | J17: allows me to select future dates past current date | K17: PASSED | M17: PASSED | O17: PASSED | Q17: PASSED | S17: PASSED | U17: PASSED | W17: PASSED | Y17: OPEN | AA17: OPEN | AC17: PASSED | AE17: FAILED | AF17: working - however, email received display the ticket ID system of CMS which does not correspond to the ticket ID shown to users, potentially creating confusion whenever getting email notifications setting this to "failed' status to bring this detail to attention | AI17: OPEN | AK17: PASSED | AM17: PASSED | AO17: PASSED
A18: US-TC-07 | C18: PASSED | E18: PASSED | G18: PASSED | I18: PASSED | K18: PASSED | M18: PASSED | O18: PASSED | Q18: PASSED | S18: PASSED | U18: PASSED | W18: PASSED | Y18: OPEN | AA18: OPEN | AC18: PASSED | AE18: OPEN | AI18: OPEN | AK18: PASSED | AM18: PASSED | AO18: PASSED
A19: US-TC-08 | C19: PASSED | E19: PASSED | I19: PASSED | K19: PASSED | M19: PASSED | O19: PASSED | Q19: PASSED | S19: PASSED | U19: PASSED | W19: PASSED | Y19: OPEN | AA19: OPEN | AC19: PASSED | AE19: OPEN | AI19: OPEN | AK19: PASSED | AM19: OPEN | AO19: OPEN
A20: US-TC-09 | C20: PASSED | E20: PASSED | I20: PASSED | K20: PASSED | M20: PASSED | O20: PASSED | Q20: PASSED | S20: PASSED | U20: PASSED | W20: PASSED | Y20: OPEN | AA20: OPEN | AC20: PASSED | AE20: OPEN | AI20: OPEN | AK20: PASSED | AM20: PASSED | AO20: OPEN
A21: US-TC-10 | C21: PASSED | E21: BLOCKED | K21: PASSED | M21: PASSED | O21: PASSED | Q21: PASSED | S21: PASSED | U21: PASSED | W21: PASSED | X21: only tested with invalid format but unable to test "unreadable/corrupted" | Y21: OPEN | AA21: OPEN | AC21: PASSED | AE21: OPEN | AI21: OPEN | AK21: PASSED | AM21: PASSED | AN21: export feature not found Hannah: The export feature is located below the table. edit: noted thank you | AO21: OPEN
A22: US-TC-11 | C22: PASSED | E22: PASSED | K22: PASSED | M22: PASSED | O22: PASSED | Q22: PASSED | S22: PASSED | U22: PASSED | W22: PASSED | Y22: OPEN | AA22: OPEN | AC22: PASSED | AE22: OPEN | AI22: OPEN | AK22: PASSED | AM22: PASSED | AO22: OPEN
A23: US-TC-12 | C23: FAILED | D23: validation is displayed only if submitted without following certain requirements. will only show them one by one and not simultaneously | E23: PASSED | K23: PASSED | M23: PASSED | O23: PASSED | Q23: PASSED | S23: PASSED | U23: PASSED | W23: PASSED | Y23: OPEN | AA23: OPEN | AC23: PASSED | AE23: OPEN | AI23: OPEN | AK23: PASSED | AM23: PASSED | AO23: OPEN
A24: US-TC-13 | C24: FAILED | D24: feature not implemented or N/A | E24: FAILED | F24: N/A or feature not implemented | K24: PASSED | M24: PASSED | O24: PASSED | Q24: PASSED | S24: PASSED | U24: PASSED | W24: PASSED | Y24: OPEN | AA24: OPEN | AC24: PASSED | AE24: OPEN | AI24: OPEN | AK24: PASSED | AM24: PASSED | AO24: OPEN
A25: US-TC-14 | C25: PASSED | D25: validation not triggered when submitting with only letters | E25: PASSED | K25: PASSED | M25: PASSED | O25: PASSED | Q25: PASSED | S25: PASSED | U25: PASSED | W25: PASSED | Y25: OPEN | AA25: OPEN | AC25: PASSED | AE25: OPEN | AI25: OPEN | AK25: PASSED | AM25: PASSED | AO25: OPEN
A26: US-TC-15 | C26: FAILED | D26: validation not triggered when submitting with future date | E26: PASSED | K26: PASSED | M26: PASSED | O26: PASSED | Q26: PASSED | S26: PASSED | U26: PASSED | W26: PASSED | Y26: OPEN | AA26: OPEN | AC26: PASSED | AE26: OPEN | AI26: OPEN | AK26: PASSED | AM26: PASSED | AO26: OPEN
A27: US-TC-16 | K27: PASSED | M27: PASSED | O27: PASSED | Q27: PASSED | S27: PASSED | U27: PASSED | W27: PASSED | Y27: OPEN | AA27: OPEN | AC27: PASSED | AE27: OPEN | AI27: OPEN | AK27: PASSED | AM27: PASSED | AO27: OPEN
A28: US-TC-17 | K28: PASSED | M28: PASSED | O28: PASSED | Q28: PASSED | S28: PASSED | U28: PASSED | W28: PASSED | Y28: OPEN | AA28: OPEN | AC28: OPEN | AE28: OPEN | AI28: OPEN | AK28: PASSED | AM28: PASSED | AO28: OPEN
A29: US-TC-18 | K29: PASSED | M29: PASSED | O29: PASSED | Q29: PASSED | S29: PASSED | U29: PASSED | W29: PASSED | Y29: OPEN | AA29: OPEN | AC29: OPEN | AE29: OPEN | AI29: OPEN | AK29: PASSED | AM29: OPEN | AN29: currently no record long enough to check at the moment | AO29: OPEN
A30: US-TC-19 | K30: PASSED | M30: PASSED | O30: PASSED | Q30: PASSED | S30: PASSED | U30: PASSED | W30: PASSED | Y30: OPEN | AA30: OPEN | AC30: OPEN | AE30: OPEN | AI30: OPEN | AK30: PASSED | AM30: OPEN | AN30: file fields are disabled even if draft status? | AO30: OPEN
A31: US-TC-20 | K31: PASSED | M31: PASSED | O31: PASSED | Q31: PASSED | S31: PASSED | U31: PASSED | W31: PASSED | Y31: OPEN | AA31: OPEN | AC31: OPEN | AI31: OPEN | AK31: PASSED | AM31: FAILED | AN31: page crashes when attempting to change status to "certificate claimed" BadMethodCallException Call to undefined method App\Models\Certificate::getCertificateTypeText() | AO31: OPEN
A32: US-TC-21 | K32: PASSED | M32: PASSED | O32: PASSED | Q32: PASSED | S32: PASSED | U32: PASSED | W32: PASSED | Y32: OPEN | AA32: OPEN | AC32: OPEN | AI32: OPEN | AK32: PASSED | AM32: PASSED | AO32: OPEN
A33: US-TC-22 | K33: PASSED | M33: PASSED | O33: PASSED | Q33: PASSED | S33: PASSED | U33: PASSED | W33: PASSED | Y33: OPEN | AA33: OPEN | AC33: OPEN | AI33: OPEN | AK33: PASSED | AM33: PASSED | AO33: OPEN
A34: US-TC-23 | K34: PASSED | M34: PASSED | O34: PASSED | Q34: PASSED | S34: PASSED | U34: PASSED | W34: PASSED | Y34: OPEN | AA34: OPEN | AC34: OPEN | AI34: OPEN | AK34: PASSED | AM34: PASSED | AO34: OPEN
A35: US-TC-24 | K35: PASSED | M35: PASSED | O35: PASSED | Q35: PASSED | S35: PASSED | U35: PASSED | W35: PASSED | Y35: OPEN | AA35: OPEN | AC35: OPEN | AI35: OPEN | AK35: PASSED | AM35: PASSED | AO35: OPEN
A36: US-TC-25 | K36: PASSED | M36: PASSED | O36: PASSED | Q36: PASSED | S36: PASSED | U36: PASSED | W36: PASSED | Y36: OPEN | AA36: OPEN | AC36: OPEN | AI36: OPEN | AK36: PASSED | AM36: FAILED | AN36: "certificate claimed" affected by page breaking from bug | AO36: OPEN
A37: US-TC-26 | K37: PASSED | M37: PASSED | O37: PASSED | Q37: PASSED | S37: PASSED | U37: PASSED | W37: PASSED | Y37: OPEN | AA37: OPEN | AC37: OPEN | AI37: OPEN | AK37: PASSED | AM37: FAILED | AN37: note field working - however entered text does not reflect in email sent to requestor | AO37: OPEN
A38: US-TC-27 | K38: PASSED | M38: PASSED | O38: PASSED | Q38: PASSED | S38: PASSED | U38: PASSED | W38: PASSED | Y38: OPEN | AA38: OPEN | AC38: OPEN | AI38: OPEN | AK38: PASSED | AM38: PASSED | AO38: OPEN
A39: US-TC-28 | K39: PASSED | M39: PASSED | O39: PASSED | Q39: PASSED | S39: PASSED | U39: PASSED | W39: PASSED | Y39: OPEN | AA39: OPEN | AC39: OPEN | AI39: OPEN | AK39: PASSED | AM39: PASSED | AO39: OPEN
A40: US-TC-29 | K40: PASSED | M40: PASSED | O40: PASSED | Q40: PASSED | S40: PASSED | U40: PASSED | W40: PASSED | Y40: OPEN | AA40: OPEN | AC40: OPEN | AI40: OPEN | AK40: PASSED | AM40: PASSED | AO40: OPEN
A41: US-TC-30 | K41: PASSED | M41: PASSED | O41: PASSED | Q41: PASSED | S41: PASSED | U41: PASSED | W41: PASSED | Y41: OPEN | AA41: OPEN | AC41: OPEN | AI41: OPEN | AK41: PASSED | AM41: PASSED
A42: US-TC-31 | K42: PASSED | M42: PASSED | O42: PASSED | Q42: PASSED | S42: FAILED | T42: primary function to save draft is working "failed" - however there was no confirmation message displayed, only redirect to dashboard unless "confirmation message" = status update? correct status displayed | U42: PASSED | W42: PASSED | Y42: OPEN | AA42: OPEN | AC42: OPEN | AI42: OPEN | AK42: FAILED | AM42: PASSED
A43: US-TC-32 | K43: PASSED | M43: PASSED | O43: PASSED | Q43: PASSED | S43: FAILED | T43: primary function to submit application working "failed" - however there was no confirmation message displayed, only redirect to dashboard unless "confirmation message" = status update? correct status displayed | U43: PASSED | W43: PASSED | Y43: OPEN | AA43: OPEN | AC43: OPEN | AI43: OPEN | AK43: PASSED | AM43: PASSED
A44: US-TC-33 | K44: PASSED | M44: PASSED | O44: PASSED | Q44: PASSED | S44: REQUEST | T44: when submitting application and triggering an error validation, page shoots back up to the top. hopefully can adjust to staying in current view/position on the page instead of having to scroll all the way down again | U44: PASSED | W44: PASSED | Y44: OPEN | AA44: OPEN | AC44: OPEN | AI44: OPEN | AK44: PASSED | AM44: PASSED
A45: US-TC-34 | K45: PASSED | M45: PASSED | O45: PASSED | Q45: PASSED | S45: OPEN | U45: PASSED | W45: PASSED | Y45: OPEN | AA45: OPEN | AC45: OPEN | AI45: OPEN | AK45: PASSED | AM45: PASSED
A46: US-TC-35 | K46: PASSED | M46: PASSED | O46: PASSED | Q46: PASSED | S46: OPEN | U46: PASSED | W46: PASSED | Y46: OPEN | AA46: OPEN | AC46: OPEN | AI46: OPEN | AK46: PASSED | AM46: PASSED
A47: US-TC-36 | K47: PASSED | M47: PASSED | O47: PASSED | Q47: PASSED | S47: OPEN | U47: PASSED | W47: PASSED | Y47: OPEN | AA47: OPEN | AC47: OPEN | AI47: OPEN | AK47: PASSED | AM47: PASSED
A48: US-TC-37 | K48: PASSED | M48: PASSED | O48: PASSED | Q48: PASSED | S48: OPEN | U48: PASSED | W48: PASSED | Y48: OPEN | AA48: OPEN | AC48: OPEN | AI48: OPEN | AK48: PASSED | AM48: PASSED
A49: US-TC-38 | K49: PASSED | M49: PASSED | O49: PASSED | Q49: PASSED | S49: OPEN | U49: PASSED | W49: PASSED | Y49: OPEN | AA49: OPEN | AC49: OPEN | AI49: OPEN | AK49: PASSED | AM49: PASSED
A50: US-TC-39 | K50: FAILED | L50: No confirmation message displayed | M50: PASSED | O50: PASSED | Q50: PASSED | S50: OPEN | U50: PASSED | W50: PASSED | Y50: OPEN | AA50: OPEN | AC50: OPEN | AI50: OPEN | AK50: PASSED | AM50: PASSED
A51: US-TC-40 | K51: PASSED | M51: PASSED | O51: PASSED | Q51: PASSED | S51: OPEN | U51: PASSED | W51: PASSED | Y51: OPEN | AA51: OPEN | AC51: OPEN | AI51: OPEN | AK51: PASSED | AM51: PASSED
A52: US-TC-41 | K52: CLARIFICATION | L52: when submitting application and triggering an error validation, page shoots back up to the top. hopefully can adjust to staying in current view/position on the page instead of having to scroll all the way down again | M52: PASSED | O52: PASSED | Q52: PASSED | S52: OPEN | U52: PASSED | W52: PASSED | Y52: OPEN | AA52: OPEN | AC52: OPEN | AI52: OPEN | AK52: PASSED | AM52: PASSED
A53: US-TC-42 | K53: OPEN | M53: PASSED | O53: PASSED | Q53: PASSED | S53: OPEN | U53: PASSED | W53: PASSED | Y53: OPEN | AA53: OPEN | AC53: OPEN | AI53: OPEN | AK53: PASSED | AM53: PASSED
A54: US-TC-43 | K54: OPEN | M54: PASSED | O54: PASSED | Q54: PASSED | S54: OPEN | U54: FAILED | V54: primary function to save as draft working "failed" - however there was no confirmation message displayed, only redirect to dashboard unless "confirmation message" = status update? correct status displayed | W54: PASSED | Y54: OPEN | AA54: OPEN | AC54: OPEN | AI54: OPEN | AK54: PASSED | AM54: PASSED
A55: US-TC-44 | K55: OPEN | M55: FAILED | N55: No confirmation message displayed | O55: PASSED | Q55: PASSED | S55: OPEN | U55: PASSED | W55: PASSED | Y55: OPEN | AA55: OPEN | AC55: OPEN | AI55: OPEN | AK55: PASSED | AM55: PASSED
A56: US-TC-45 | K56: OPEN | M56: PASSED | O56: PASSED | Q56: PASSED | S56: OPEN | U56: REQUEST | V56: when submitting application and triggering an error validation, page shoots back up to the top. hopefully can adjust to staying in current view/position on the page instead of having to scroll all the way down again | W56: PASSED | Y56: OPEN | AA56: OPEN | AC56: OPEN | AI56: OPEN | AK56: PASSED | AM56: PASSED
A57: US-TC-46 | K57: OPEN | M57: REQUEST | N57: when submitting application and triggering an error validation, page shoots back up to the top. hopefully can adjust to staying in current view/position on the page instead of having to scroll all the way down again | O57: PASSED | Q57: PASSED | S57: OPEN | U57: FAILED | V57: primary function to submit application working "failed" - however there was no confirmation message displayed, only redirect to dashboard unless "confirmation message" = status update? correct status displayed | W57: PASSED | Y57: OPEN | AA57: OPEN | AC57: OPEN | AI57: OPEN | AK57: PASSED | AM57: PASSED
A58: US-TC-47 | K58: OPEN | M58: OPEN | O58: PASSED | Q58: PASSED | S58: OPEN | U58: REQUEST | V58: when submitting application and triggering an error validation, page shoots back up to the top. hopefully can adjust to staying in current view/position on the page instead of having to scroll all the way down again | W58: PASSED | Y58: OPEN | AA58: OPEN | AC58: OPEN | AI58: OPEN | AK58: PASSED | AM58: PASSED
A59: US-TC-48 | K59: OPEN | M59: OPEN | O59: PASSED | Q59: PASSED | S59: OPEN | U59: FAILED | V59: no email & sms received by requestor no email received by admin | W59: PASSED | Y59: OPEN | AA59: OPEN | AC59: OPEN | AI59: OPEN | AK59: PASSED | AM59: PASSED
A60: US-TC-49 | K60: OPEN | M60: OPEN | O60: PASSED | Q60: PASSED | S60: OPEN | U60: FAILED | V60: no email & sms received by requestor no email received by admin | W60: REQUEST | X60: same as requesting for "Draft" status removal from admin databse, including removing email template | Y60: OPEN | AA60: OPEN | AC60: OPEN | AI60: OPEN | AK60: PASSED | AM60: PASSED
A61: US-TC-50 | K61: OPEN | M61: OPEN | O61: PASSED | Q61: PASSED | U61: FAILED | V61: no email & sms received by requestor | W61: REQUEST | X61: same as requesting for "Draft" status removal from admin databse, including removing email template | Y61: OPEN | AA61: OPEN | AC61: OPEN | AI61: OPEN | AK61: PASSED | AM61: OPEN
A62: US-TC-51 | K62: OPEN | M62: OPEN | O62: PASSED | Q62: PASSED | U62: FAILED | V62: no email & sms received by requestor | W62: FAILED | X62: no SMS and email received by requestor no admin email | Y62: OPEN | AA62: OPEN | AC62: OPEN | AI62: OPEN | AK62: PASSED | AM62: OPEN
A63: US-TC-52 | K63: OPEN | M63: OPEN | O63: FAILED | P63: primary function to save draft is working "failed" - however there was no confirmation message displayed, only redirect to dashboard correct status displayed | Q63: PASSED | U63: FAILED | V63: received email but text provided by admin for "reason for revision" and "author's notes" not showing in email and sms | W63: FAILED | X63: no SMS and email received by requestor no admin email | Y63: OPEN | AA63: OPEN | AC63: OPEN | AI63: OPEN | AK63: PASSED | AM63: OPEN
A64: US-TC-53 | K64: OPEN | M64: OPEN | O64: FAILED | P64: primary function to submit application working "failed" - however there was no confirmation message displayed, only redirect to dashboard correct status displayed | Q64: PASSED | U64: FAILED | V64: received email but text provided by admin for "reason for revision" and "author's notes" not showing in email and sms | W64: FAILED | X64: no SMS and email received by requestor no admin email | Y64: OPEN | AA64: OPEN | AC64: OPEN | AI64: OPEN | AK64: PASSED | AM64: OPEN
A65: US-TC-54 | K65: OPEN | M65: OPEN | O65: REQUEST | P65: when submitting application and triggering an error validation, page shoots back up to the top. hopefully can adjust to staying in current view/position on the page instead of having to scroll all the way down again | Q65: PASSED | U65: FAILED | V65: email working but no SMS | W65: FAILED | X65: no SMS and email received by requestor no admin email | Y65: OPEN | AA65: OPEN | AC65: OPEN | AI65: OPEN | AK65: PASSED | AM65: OPEN
A66: US-TC-55 | K66: OPEN | M66: OPEN | O66: OPEN | Q66: PASSED | U66: FAILED | V66: email working but no SMS | W66: FAILED | X66: working - but reason for revision & admin notes not displayed | Y66: OPEN | AA66: OPEN | AC66: OPEN | AI66: OPEN | AK66: PASSED | AM66: OPEN
A67: US-TC-56 | K67: OPEN | M67: OPEN | O67: OPEN | Q67: PASSED | U67: FAILED | V67: no email & sms received by requestor no email received by admin | W67: FAILED | X67: working - but reason for revision & admin notes not displayed | Y67: OPEN | AA67: OPEN | AC67: OPEN | AI67: OPEN | AK67: OPEN | AM67: OPEN
A68: US-TC-57 | K68: OPEN | M68: OPEN | O68: OPEN | Q68: PASSED | U68: FAILED | V68: no email & sms received by requestor no email received by admin | W68: FAILED | X68: no SMS received | Y68: OPEN | AA68: OPEN | AC68: OPEN | AI68: OPEN | AK68: PASSED | AM68: OPEN
A69: US-TC-58 | K69: OPEN | M69: OPEN | O69: OPEN | Q69: PASSED | U69: PASSED | W69: OPEN | Y69: OPEN | AA69: OPEN | AC69: OPEN | AI69: OPEN | AK69: PASSED | AM69: OPEN
A70: US-TC-59 | K70: OPEN | M70: OPEN | O70: OPEN | Q70: PASSED | R70: works but validation displayed is standard " This field is required." which is fine submission is blocked unless checkbox is seleted | U70: PASSED | W70: OPEN | Y70: OPEN | AA70: OPEN | AC70: OPEN | AI70: OPEN | AK70: PASSED | AM70: OPEN
A71: US-TC-60 | K71: OPEN | M71: OPEN | O71: OPEN | Q71: FAILED | R71: primary function to save draft is working "failed" - however there was no confirmation message displayed, only redirect to dashboard correct status displayed | U71: PASSED | W71: OPEN | Y71: OPEN | AA71: OPEN | AC71: OPEN | AI71: OPEN | AK71: PASSED | AM71: OPEN
A72: US-TC-61 | M72: OPEN | O72: OPEN | Q72: FAILED | R72: primary function to submit application working "failed" - however there was no confirmation message displayed, only redirect to dashboard correct status displayed | U72: PASSED | W72: OPEN | Y72: OPEN | AA72: OPEN | AC72: OPEN | AI72: OPEN | AK72: PASSED | AM72: OPEN
A73: US-TC-62 | M73: OPEN | O73: OPEN | Q73: REQUEST | R73: when submitting application and triggering an error validation, page shoots back up to the top. hopefully can adjust to staying in current view/position on the page instead of having to scroll all the way down again | U73: FAILED | V73: page breaks into code when changing to status "certificate claimed" | W73: OPEN | Y73: OPEN | AA73: OPEN | AC73: OPEN | AI73: OPEN | AK73: PASSED | AM73: OPEN
A74: US-TC-63 | O74: OPEN | Q74: OPEN | U74: FAILED | V74: page breaks into code when changing to status "certificate claimed" | W74: OPEN | Y74: OPEN | AA74: OPEN | AC74: OPEN | AI74: OPEN | AK74: PASSED | AM74: OPEN
A75: US-TC-64 | O75: OPEN | Q75: OPEN | W75: OPEN | AA75: OPEN | AC75: OPEN | AI75: OPEN | AK75: PASSED | AM75: OPEN
A76: US-TC-65 | O76: OPEN | Q76: OPEN | W76: OPEN | AA76: OPEN | AC76: OPEN | AI76: OPEN | AK76: PASSED | AM76: OPEN
A77: US-TC-66 | O77: OPEN | Q77: OPEN | W77: OPEN | AA77: OPEN | AC77: OPEN | AI77: OPEN | AK77: OPEN | AL77: The request ID should be left-padded with zeros to a length of 5. | AM77: OPEN
A78: US-TC-67 | O78: OPEN | Q78: OPEN | AA78: OPEN | AC78: OPEN | AI78: OPEN | AK78: PASSED | AM78: OPEN
A79: US-TC-68 | O79: OPEN | Q79: OPEN | AA79: OPEN | AC79: OPEN | AI79: OPEN | AK79: PASSED | AM79: OPEN
A80: US-TC-69 | O80: OPEN | Q80: OPEN | AA80: OPEN | AC80: OPEN | AK80: PASSED | AM80: OPEN
A81: US-TC-70 | O81: OPEN | Q81: OPEN | AA81: OPEN | AC81: OPEN | AK81: PASSED | AM81: OPEN
A82: US-TC-71 | Q82: OPEN | AA82: OPEN | AC82: OPEN | AK82: PASSED | AM82: OPEN
A83: US-TC-72 | Q83: OPEN | AA83: OPEN | AK83: PASSED | AM83: OPEN
A84: US-TC-73 | Q84: OPEN | AK84: PASSED | AM84: OPEN
A85: US-TC-74 | Q85: OPEN | AK85: PASSED | AM85: OPEN
A86: US-TC-75 | Q86: OPEN | AK86: OPEN | AL86: The request ID should be left-padded with zeros to a length of 5. | AM86: OPEN
A87: US-TC-76 | Q87: OPEN | AK87: PASSED | AM87: OPEN
A88: US-TC-77 | Q88: OPEN | AK88: PASSED | AM88: OPEN
A89: US-TC-78 | Q89: OPEN | AK89: PASSED | AM89: OPEN
A90: US-TC-79 | AK90: PASSED | AM90: OPEN
A91: US-TC-80 | AK91: PASSED | AM91: OPEN
A92: US-TC-81 | AK92: PASSED | AM92: OPEN
A93: US-TC-82 | AK93: PASSED | AM93: OPEN
A94: US-TC-83 | AK94: PASSED | AM94: OPEN
A95: US-TC-84 | AK95: PASSED | AM95: OPEN
A96: US-TC-85 | AK96: PASSED | AM96: OPEN
A97: US-TC-86 | AK97: PASSED | AM97: OPEN
A98: US-TC-87 | AM98: OPEN
A99: US-TC-88 | AM99: OPEN
A100: US-TC-89 | AM100: OPEN
A101: US-TC-90 | AM101: OPEN
A102: US-TC-91 | AM102: OPEN
A103: US-TC-92 | AM103: OPEN
...

Sheet PG-US-01
A1: PG-US-01 | B1: USER STORY: As a new user, I want to click the 'New? Sign Up' button on the login page so that I can access the registration form and create an account.
A2: Test Case ID | B2: Test Objective | C2: Preconditions | D2: Test Steps | E2: Expected Results | F2: Status | G2: Comments/Issue
A3: =IF(B3<>"", "US-1-TC-" & TEXT(COUNTA($B$3:B3), "00"), "") -> US-1-TC-01 | B3: Verify that clicking the 'New? Sign Up' button on the Login page redirects the user to the Registration Form of the Assessor’s Office. | C3: 1. User must be on the Sta. Rosa Payroll Portal. 2. User must be on the Login page. | D3: 1. Search Assessor office login | E3: The registration form is displayed with the following required fields marked with an asterisk (*) and appropriate placeholders or labels: A note is shown: “Please fill out the fields below with your information. All fields with asterisks (*) are required. a) First Name* b) Middle Name c) Last Name* d) Date of Birth (dd/mm/yyyy)* e) Contact Number* f) Email Address* g) New Password* h) Confirm Password* A checkbox for "I agree to the Terms & Conditions of the City of Sta Rosa" Click the Submit button for the creation of account. | F3: PASSED
A4: =IF(B4<>"", "US-1-TC-" & TEXT(COUNTA($B$3:B4), "00"), "") -> US-1-TC-02 | B4: Verify that the system accepts a valid contact number that starts with '09' in the Contact Number field. | C4: 1. User must be on the Sta. Rosa Payroll Portal. 2. User must be on the Login page. 3. User must click the "New Sign-up" button. | D4: 1. Search Assessor office login 2. Click the "New?Sign up" button below the forget password. 3. Fill out the First Name Field 4. Fill out Middle Name Field 5. Fill out the Last Name Field 6. Fill out the Date of Birth 7. Fill out the Contact Number by 09 8. Fill out the Email Address Field 9. Set the Password on the New Password Field 10. Confirm the Password on the Confirm Password Field 11. Click the checkbox on T&C 12. Click Submit Button | E4: The registration form is displayed with the following required fields marked with an asterisk (*) and appropriate placeholders or labels: A note is shown: “Please fill out the fields below with your information. All fields with asterisks (*) are required. a) First Name* b) Middle Name c) Last Name* d) Date of Birth (dd/mm/yyyy)* e) Contact Number* f) Email Address* g) New Password* h) Confirm Password* A checkbox for "I agree to the Terms & Conditions of the City of Sta Rosa" Click the Submit button for the creation of account. After that it will go the Assessor Office confirmation message This confirmation message consist of the message: Assessor’s Office Thank you! Please check your e-mail inbox for verification. [Back to Home] button | F4: FAILED | G4: It accepts contact numbers that start with '09', but it also accepts inputs even if all the characters are not numeric.
A5: =IF(B5<>"", "US-1-TC-" & TEXT(COUNTA($B$3:B5), "00"), "") -> US-1-TC-03 | B5: Verify that the system accepts a valid contact number that starts with '639' in the Contact Number field. | C5: 1. User must be on the Sta. Rosa Payroll Portal. 2. User must be on the Login page. 3. User must click the "New Sign-up" button. | D5: 1. Search Assessor office login 2. Click the "New?Sign up" button below the forget password. 3. Fill out the First Name Field 4. Fill out Middle Name Field 5. Fill out the Last Name Field 6. Fill out the Date of Birth 7. Fill out the Contact Number by 639 8. Fill out the Email Address Field 9. Set the Password on the New Password Field 10. Confirm the Password on the Confirm Password Field 11. Click the checkbox on T&C 12. Click Submit Button | E5: The registration form is displayed with the following required fields marked with an asterisk (*) and appropriate placeholders or labels: A note is shown: “Please fill out the fields below with your information. All fields with asterisks (*) are required. a) First Name* b) Middle Name c) Last Name* d) Date of Birth (dd/mm/yyyy)* e) Contact Number* f) Email Address* g) New Password* h) Confirm Password* A checkbox for "I agree to the Terms & Conditions of the City of Sta Rosa" Click the Submit button for the creation of account. After that it will go the Assessor Office confirmation message This confirmation message consist of the message: Assessor’s Office Thank you! Please check your e-mail inbox for verification. [Back to Home] button | F5: FAILED | G5: It accepts contact numbers that start with '639', but it also accepts inputs even if all the characters are not numeric.
A6: =IF(B6<>"", "US-1-TC-" & TEXT(COUNTA($B$3:B6), "00"), "") -> US-1-TC-04 | B6: Verify that the system accepts a properly formatted email address (e.g., juandela@cruz.com) in the Email field. | C6: 1. User must be on the Sta. Rosa Payroll Portal. 2. User must be on the Login page. 3. User must click the "New Sign-up" button. | D6: 1. Search Assessor office login 2. Click the "New?Sign up" button below the forget password. 3. Fill out the First Name Field 4. Fill out Middle Name Field 5. Fill out the Last Name Field 6. Fill out the Date of Birth 7. Fill out the Contact Number 8. Fill out the Email Address Field with a valid email address "@" 9. Set the Password on the New Password Field 10. Confirm the Password on the Confirm Password Field 11. Click the checkbox on T&C 12. Click Submit Button | E6: The registration form is displayed with the following required fields marked with an asterisk (*) and appropriate placeholders or labels: A note is shown: “Please fill out the fields below with your information. All fields with asterisks (*) are required. a) First Name* b) Middle Name c) Last Name* d) Date of Birth (dd/mm/yyyy)* e) Contact Number* f) Email Address* g) New Password* h) Confirm Password* A checkbox for "I agree to the Terms & Conditions of the City of Sta Rosa" Click the Submit button for the creation of account. After that it will go the Assessor Office confirmation message This confirmation message consist of the message: Assessor’s Office Thank you! Please check your e-mail inbox for verification. [Back to Home] button | F6: PASSED
A7: =IF(B7<>"", "US-1-TC-" & TEXT(COUNTA($B$3:B7), "00"), "") -> US-1-TC-05 | B7: Verify that the system prevents form submission and displays an error when an invalid email address (e.g., juandelacruz) is entered. | C7: 1. User must be on the Sta. Rosa Payroll Portal. 2. User must be on the Login page. 3. User must click the "New Sign-up" button. | D7: 1. Search Assessor office login 2. Click the "New?Sign up" button below the forget password. 3. Fill out the First Name Field 4. Fill out Middle Name Field 5. Fill out the Last Name Field 6. Fill out the Date of Birth 7. Fill out the Contact Number 8. Fill out the Email Address Field with a valid email address "@" 9. Set the Password on the New Password Field 10. Confirm the Password on the Confirm Password Field 11. Click the checkbox on T&C 12. Click Submit Button | E7: An error message will be displayed if the email entered is invalid. | F7: PASSED
A8: =IF(B8<>"", "US-1-TC-" & TEXT(COUNTA($B$3:B8), "00"), "") -> US-1-TC-06 | B8: Verify that the system accepts a strong password that includes special characters or alphanumeric combinations. | C8: 1. User must be on the Sta. Rosa Payroll Portal. 2. User must be on the Login page. 3. User must click the "New Sign-up" button. | D8: 1. Search Assessor office login 2. Click the ""New?Sign up"" button below the forget password. 3. Fill out the First Name Field 4. Fill out Middle Name Field 5. Fill out the Last Name Field 6. Fill out the Date of Birth 7. Fill out the Contact Number 8. Fill out the Email Address Field 9. Set the Password on the New Password Field with special characters or strings 10. Confirm the Password on the Confirm Password Field 11. Click the checkbox on T&C 12. Click Submit Button | E8: The registration form is displayed with the following required fields marked with an asterisk (*) and appropriate placeholders or labels: A note is shown: “Please fill out the fields below with your information. All fields with asterisks (*) are required. a) First Name* b) Middle Name c) Last Name* d) Date of Birth (dd/mm/yyyy)* e) Contact Number* f) Email Address* g) New Password* h) Confirm Password* A checkbox for "I agree to the Terms & Conditions of the City of Sta Rosa" Click the Submit button for the creation of account. After that it will go the Assessor Office confirmation message This confirmation message consist of the message: Assessor’s Office Thank you! Please check your e-mail inbox for verification. [Back to Home] button | F8: PASSED
A9: =IF(B9<>"", "US-1-TC-" & TEXT(COUNTA($B$3:B9), "00"), "") -> US-1-TC-07 | B9: Verify that the system prevents form submission when the Confirm Password field does not match the New Password field. | C9: 1. User must be on the Sta. Rosa Payroll Portal. 2. User must be on the Login page. 3. User must click the "New Sign-up" button. | D9: 1. Search Assessor office login 2. Click the ""New?Sign up"" button below the forget password. 3. Fill out the First Name Field 4. Fill out Middle Name Field 5. Fill out the Last Name Field 6. Fill out the Date of Birth 7. Fill out the Contact Number 8. Fill out the Email Address Field 9. Set the Password on the New Password Field with special characters or strings 10. Confirm the Password with wrong characteds on the Confirm Password Field | E9: The user will receive a inline field warning if the confirmation password does not match the original password | F9: PASSED
A10: =IF(B10<>"", "US-1-TC-" & TEXT(COUNTA($B$3:B10), "00"), "") -> US-1-TC-08 | B10: Verify that the Submit button will not proceed if the Terms & Conditions checkbox is not checked. | C10: 1. User must be on the Sta. Rosa Payroll Portal. 2. User must be on the Login page. 3. User must click the "New Sign-up" button. | D10: 1. Search Assessor office login 2. Click the ""New?Sign up"" button below the forget password. 3. Fill out the First Name Field 4. Fill out Middle Name Field 5. Fill out the Last Name Field 6. Fill out the Date of Birth 7. Fill out the Contact Number 8. Fill out the Email Address Field 9. Set the Password on the New Password Field with special characters or strings 10. Confirm the Password on the Confirm Password Field 11. Click the checkbox on T&C 12. Click Submit Button | E10: Will received a pop up warning that the checkbox of T&C is not yet check. Should no proceed it not. | F10: PASSED
A11: =IF(B11<>"", "US-1-TC-" & TEXT(COUNTA($B$3:B11), "00"), "") -> US-1-TC-09 | B11: Verify that the Assessor’s Office Registration form displays required field validation messages when any mandatory field is left unanswered. | C11: 1. User must be on the Sta. Rosa Payroll Portal. 2. User must be on the Login page. 3. User must click the "New Sign-up" button. | D11: 1. Search Assessor office login 2. Click the ""New?Sign up"" button below the forget password. 3. Fill out the First Name Field 4. Fill out Middle Name Field 5. Fill out the Last Name Field 6. Fill out the Date of Birth 7. Fill out the Contact Number 8. Fill out the Email Address Field 9. Set the Password on the New Password Field with special characters or strings 10. Confirm the Password on the Confirm Password Field 11. Click the checkbox on T&C 12. Click Submit Button | E11: The registration form is displayed with the following required fields marked with an asterisk (*) and appropriate placeholders or labels: A note is shown: “Please fill out the fields below with your information. All fields with asterisks (*) are required. a) First Name* b) Middle Name c) Last Name* d) Date of Birth (dd/mm/yyyy)* e) Contact Number* f) Email Address* g) New Password* h) Confirm Password* A checkbox for "I agree to the Terms & Conditions of the City of Sta Rosa" Click the Submit button for the creation of account. After that it will go the Assessor Office confirmation message This confirmation message consist of the message: Assessor’s Office Thank you! Please check your e-mail inbox for verification. [Back to Home] button | F11: PASSED
A12: =IF(B12<>"", "US-1-TC-" & TEXT(COUNTA($B$3:B12), "00"), "") -> US-1-TC-10 | B12: Verifiy that after clicking the Registration button will be directed to Please Verify Login. | C12: 1. User must be on the Sta. Rosa Payroll Portal. 2. User must be on the Login page. 3. User must click the "New Sign-up" button. | F12: PASSED
A13: =IF(B13<>"", "US-1-TC-" & TEXT(COUNTA($B$3:B13), "00"), "") -> US-1-TC-11 | B13: Verify that clicking the 'Back to Home' button redirects the user to the Login page | C13: 1. User must be on the Sta. Rosa Payroll Portal. 2. User must be on the Login page. 3. User must click the "New Sign-up" button. | F13: PASSED
A14: =IF(B14<>"", "US-1-TC-" & TEXT(COUNTA($B$3:B14), "00"), "") -> US-1-TC-12 | B14: Verify that the password requirements are clearly indicated before any input is made. -Jed | C14: 1. User must be on the Sta. Rosa Payroll Portal. 2. User must be on the Login page. 3. User must click the "New Sign-up" button. | E14: The requirements, "Password must be at least 8 characters long and include at least one uppercase letter, one lowercase letter, one number, and one special character." Indicated clearly when creating a password. | F14: FAILED | G14: validation is displayed only if submitted without following certain requirements. will only show them one by one and not simultaneously
A15: =IF(B15<>"", "US-1-TC-" & TEXT(COUNTA($B$3:B15), "00"), "") -> US-1-TC-13 | B15: Verify that the password field in registration has a hide/show password toggle. -Jed | C15: 1. User must be on the Sta. Rosa Payroll Portal. 2. User must be on the Login page. 3. User must click the "New Sign-up" button. | E15: Password field having a button to toggle between hide and show. | F15: FAILED | G15: feature not implemented or N/A
A16: =IF(B16<>"", "US-1-TC-" & TEXT(COUNTA($B$3:B16), "00"), "") -> US-1-TC-14 | B16: Verify that the contact number field in registration won't allow alphabetic characters. -Jed | C16: 1. User must be on the Sta. Rosa Payroll Portal. 2. User must be on the Login page. 3. User must click the "New Sign-up" button. | E16: The system won't allow registration when the field for contact number contains letters. | F16: PASSED | G16: validation not triggered when submitting with only letters
A17: =IF(B17<>"", "US-1-TC-" & TEXT(COUNTA($B$3:B17), "00"), "") -> US-1-TC-15 | B17: Verify if the registration won't go through if the user's birth date is set in a future date. -Jed | C17: 1. User must be on the Sta. Rosa Payroll Portal. 2. User must be on the Login page. 3. User must click the "New Sign-up" button. | E17: The system won't allow registration when the user's birth date is beyond the current date. | F17: FAILED | G17: validation not triggered when submitting with future date

Sheet PG-US-02
A1: PG-US-02 | B1: USER STORY: As a registered user of the Assessor’s Office portal, I want to log in using my email and password, So that I can access my personal records and services provided by the City of Sta. Rosa.
A2: Test Case ID | B2: Test Objective | C2: Preconditions | D2: Test Steps | E2: Expected Results | F2: Status | G2: Comments
A3: =IF(B3<>"", "US-2-TC-" & TEXT(COUNTA($B$3:B3), "00"), "") -> US-2-TC-01 | B3: Verify that the login form loads correctly in the user interface. | C3: 1. User must be on the Sta. Rosa Payroll Portal. 2. User must be on the Login page. | D3: 1. Search Assessor office login 2. Navigate to the login page. | E3: The Assessor Office Login Page consists of the following elements: a) Email address field b) Password field c) Terms & Conditions checkbox d) Submit button e) Forgot Password link f) "New? Sign up" button | F3: PASSED
A4: =IF(B4<>"", "US-2-TC-" & TEXT(COUNTA($B$3:B4), "00"), "") -> US-2-TC-02 | B4: Verify that the system can able to log in using a registered email and password. | C4: 1. User must be on the Sta. Rosa Payroll Portal. 2. User must be on the Login page. | D4: 1. Search Assessor office login 2. Fill out the Email Address field with a registered email address 3. Fill out the Password field with a registered password 4. Click the checkbox of T&C 5. Click the Submit button | E4: After entering a registered email and password: a) Message is displayed: "Thank you!" "Please check your email inbox for verification." b) "Back to Home" button is shown. c) Clicking the "Back to Home" button redirects the user to the home page. After logging in with a verified new account, the user is redirected to the Assessor’s Office Dashboard, which includes the following elements: Assessor’s Office label a) Profile link b) Logout button Main Page Content: a) Welcome message for new accounts (e.g., “Welcome to the Assessor’s Office Portal!”) b) "New Request" button for submitting a new request | F4: PASSED
A5: =IF(B5<>"", "US-2-TC-" & TEXT(COUNTA($B$3:B5), "00"), "") -> US-2-TC-03 | B5: Verify that the system prevents to login when an invalid email is entered. | C5: 1. User must be on the Sta. Rosa Payroll Portal. 2. User must be on the Login page. | D5: 1. Search Assessor office login 2. Fill out the Email Address field with a invalid email address 3. Fill out the Password field 4. Click the checkbox of T&C 5. Click the Submit button | E5: The Assessor Office Login Page consists of the following elements: a) Email address field - Display an error message of "Please check your inputs, ensure that you input the same email address that you used upon registration, and your password is correct." b) Password field c) Terms & Conditions checkbox d) Submit button e) "New? Sign up" button f) Forgot Password link | F5: PASSED
A6: =IF(B6<>"", "US-2-TC-" & TEXT(COUNTA($B$3:B6), "00"), "") -> US-2-TC-04 | B6: Verify that the system prevents to login when an invalid password is entered. | C6: 1. User must be on the Sta. Rosa Payroll Portal. 2. User must be on the Login page. | D6: 1. Search Assessor office login 2. Fill out the Email Address field 3. Fill out the Password field with invalid password 4. Click the checkbox of T&C 5. Click the Submit button | E6: The Assessor Office Login Page consists of the following elements: a) Email address field - Display an error message of "Please check your inputs, ensure that you input the same email address that you used upon registration, and your password is correct." b) Password field c) Terms & Conditions checkbox d) Submit button e) "New? Sign up" button f) Forgot Password link | F6: PASSED
A7: =IF(B7<>"", "US-2-TC-" & TEXT(COUNTA($B$3:B7), "00"), "") -> US-2-TC-05 | B7: Verify that the system prevents to login when user is not registered. | C7: 1. User must be on the Sta. Rosa Payroll Portal. 2. User must be on the Login page. | D7: 1. Search Assessor office login 2. Fill out the Email Address field with a unregistered email address 3. Fill out the Password field with unregistered password 4. Click the checkbox of T&C 5. Click the Submit button | E7: The Assessor Office Login Page consists of the following elements: a) Email address field b) Password field c) Terms & Conditions checkbox d) Submit button e) Forgot Password link f) "New? Sign up" button - Display an error message of "Please check your inputs, ensure that you input the same email address that you used upon registration, and your password is correct." | F7: PASSED
A8: =IF(B8<>"", "US-2-TC-" & TEXT(COUNTA($B$3:B8), "00"), "") -> US-2-TC-06 | B8: Verify that the submit button is disabled when T&C is unchecked | C8: 1. User must be on the Sta. Rosa Payroll Portal. 2. User must be on the Login page. | D8: 1. Search Assessor office login 2. Fill out the Email Address field with a registered email address 3. Fill out the Password field 4. Do not click the checkbox of T&C 5. Click the Submit button | E8: The Assessor Office Login Page consists of the following elements: a) Email address field b) Password field c) Terms & Conditions checkbox d) Submit button e) Forgot Password link f) "New? Sign up" button - If the Terms & Conditions checkbox is not checked, a validation message appears: "Please accept the Terms & Conditions to proceed." | F8: FAILED | G8: triggers T&C validation but button does not disable
A9: =IF(B9<>"", "US-2-TC-" & TEXT(COUNTA($B$3:B9), "00"), "") -> US-2-TC-07 | B9: Verify that the system displays a required field when the Email, Password, or Terms & Conditions checkbox is left empty. | C9: 1. User must be on the Sta. Rosa Payroll Portal. 2. User must be on the Login page. | D9: 1. Search Assessor office login 2. Do not fill out the Email Address field 3. Do not fill out the Password field 4. Do not click the checkbox of T&C 5. Click the Submit button | E9: The Assessor Office Login Page consists of the following elements: a) Email address field b) Password field c) Terms & Conditions checkbox d) Submit button e) Forgot Password link f) "New? Sign up" button A required field validation message will appear if any of the following are left empty: i. Email address field: "The email field is required." or "The email must be a valid email address." ii. Password field: "The password field is required." iii. Terms & Conditions checkbox: "Please accept the Terms & Conditions to proceed." | F9: PASSED
A10: =IF(B10<>"", "US-2-TC-" & TEXT(COUNTA($B$3:B10), "00"), "") -> US-2-TC-08 | B10: Verify Forgot Password link navigates to reset page | C10: 1. User must be on the Sta. Rosa Payroll Portal. 2. User must be on the Login page. | D10: 1. Search Assessor office login 2. Click the Forgot Password link | E10: The Forgot Password page will have the following details: a) "A reset link will be sent to your email address." b) "Input your registered email address." c) Email Address field d) Send Password Reset Link button | F10: PASSED
A11: =IF(B11<>"", "US-2-TC-" & TEXT(COUNTA($B$3:B11), "00"), "") -> US-2-TC-09 | B11: Verify if the password requires at least one symbol, one lowercase letter, one uppercase letter, and one number | C11: 1. User must be on the Sta. Rosa Payroll Portal. 2. User must be on the Login page. | D11: 1. Search Assessor office login 2. Click the Forgot Password link | F11: PASSED
A12: =IF(B12<>"", "US-2-TC-" & TEXT(COUNTA($B$3:B12), "00"), "") -> US-2-TC-10 | B12: Able to submit the new password credentials even without meeting the required password security criteria | C12: 1. User must be on the Sta. Rosa Payroll Portal. 2. User must be on the Login page. | D12: 1. Search Assessor office login 2. Click the Forgot Password link | F12: BLOCKED
A13: =IF(B13<>"", "US-2-TC-" & TEXT(COUNTA($B$3:B13), "00"), "") -> US-2-TC-11 | B13: Verify that if the password and confirm password do not match, an appropriate error message is displayed | C13: 1. User must be on the Sta. Rosa Payroll Portal. 2. User must be on the Login page. | D13: 1. Search Assessor office login 2. Click the Forgot Password link | F13: PASSED
A14: =IF(B14<>"", "US-2-TC-" & TEXT(COUNTA($B$3:B14), "00"), "") -> US-2-TC-12 | B14: Verify that the user receives a reset password email after using the Forgot Password feature. | C14: 1. User must be on the Sta. Rosa Payroll Portal. 2. User must be on the Login page. | D14: 1. Search Assessor office login 2. Click the Forgot Password link | F14: PASSED
A15: =IF(B15<>"", "US-2-TC-" & TEXT(COUNTA($B$3:B15), "00"), "") -> US-2-TC-13 | B15: Verify that there is a toggle to show or hide the Password and Confirm Password fields. | C15: 1. User must be on the Sta. Rosa Payroll Portal. 2. User must be on the Login page. | D15: 1. Search Assessor office login 2. Click the Forgot Password link | F15: FAILED | G15: N/A or feature not implemented
A16: =IF(B16<>"", "US-2-TC-" & TEXT(COUNTA($B$3:B16), "00"), "") -> US-2-TC-14 | B16: Verify Sign Up link navigates to registration page | C16: 1. User must be on the Sta. Rosa Payroll Portal. 2. User must be on the Login page. | D16: 1. Search Assessor office login 2. Click the New?Sign up button | E16: The Assessor Office Login Page consists of the following elements: a) Email address field b) Password field c) Terms & Conditions checkbox d) Submit button e) Forgot Password link f) "New? Sign up" button The registration form is displayed with the following required fields marked with an asterisk (*) and appropriate placeholders or labels: A note is shown: “Please fill out the fields below with your information. All fields with asterisks (*) are required. a) First Name* b) Middle Name c) Last Name* d) Date of Birth (dd/mm/yyyy)* e) Contact Number* f) Email Address* g) New Password* h) Confirm Password* A checkbox for "I agree to the Terms & Conditions of the City of Sta Rosa" Click the Submit button for the creation of account. | F16: PASSED
A17: =IF(B17<>"", "US-2-TC-" & TEXT(COUNTA($B$3:B17), "00"), "") -> US-2-TC-15 | B17: Verify password input is masked | C17: 1. User must be on the Sta. Rosa Payroll Portal. 2. User must be on the Login page. | D17: 1. Search Assessor office login 2. Fill out the Email Address field with a registered email address 3. Fill out the Password field with a registered password | E17: The characters entered in the Password field should appear as masked characters (e.g., ••••••) | F17: PASSED

Sheet PG-US-03
A1: PG-US-03 | B1: USER STORY: As a new user of the Assessor’s Office portal, I want to see a confirmation message after submitting my email for verification, So that I know the next steps and can return to the homepage easily.
A2: Test Case ID | B2: Test Objective | C2: Preconditions | D2: Test Steps | E2: Expected Results | F2: Status | G2: Comments
A3: =IF(B3<>"", "US-3-TC-" & TEXT(COUNTA($B$4:B4), "00"), "") -> US-3-TC-01 | B3: Verify that the system sends a verification OTP email upon registration. | C3: 1. User must be on the Sta. Rosa Payroll Portal. 2. User must be on the Login page. | D3: 1. Search Assessor office login 2. Login with registered email and password and checkbox of T&C. 3. Click Submit button 4. Check OTP Verification sent on email. 5. Put the OTP on the Verification | E3: The user is redirected to a confirmation screen displaying the following: a) "Assessor’s Office" header b) "One-Time Passcode c) A message is displayed: "An email verification has been sent to your email address. Please click on the link within 15 minutes in order to proceed." d) An OTP input field labeled as "Input OTP Code" is shown. e) Didn't receive the OTP on your email address? text field below f) "Click here to resend" link for request OTP g) Submit button | F3: PASSED
A4: =IF(B4<>"", "US-3-TC-" & TEXT(COUNTA($B$4:B5), "00"), "") -> US-3-TC-02 | B4: Verify that the system sends a verification OTP email upon logging in. | C4: 1. User must be on the Sta. Rosa Payroll Portal. 2. User must be on the Login page. | D4: 1. Search Assessor office login 2. Login with registered email and password and checkbox of T&C. 3. Click Submit button 4. Check OTP Verification sent on email. 5. Put the OTP on the Verification | E4: The user is redirected to a confirmation screen displaying the following: a) "Assessor’s Office" header b) "One-Time Passcode c) A message is displayed: "An email verification has been sent to your email address. Please click on the link within 15 minutes in order to proceed." d) An OTP input field labeled as "Input OTP Code" is shown. e) Didn't receive the OTP on your email address? text field below f) "Click here to resend" link for request OTP g) Submit button | F4: PASSED
A5: =IF(B5<>"", "US-3-TC-" & TEXT(COUNTA($B$4:B6), "00"), "") -> US-3-TC-03 | B5: Verify that the user is able to enter a valid One-Time PIN (OTP) on the OTP verification page and is successfully redirected to the dashboard. | C5: 1. User must be on the Sta. Rosa Payroll Portal. 2. User must be on the Login page. | D5: 1. Search Assessor office login 2. Login with registered email and password and checkbox of T&C. 3. Click Submit button 4. Check OTP Verification sent on email. 5. Put the valid OTP on the Verification 6. Click submit or press enter | E5: The user is redirected to a confirmation screen displaying the following: a) "Assessor’s Office" header b) "One-Time Passcode c) A message is displayed: "An email verification has been sent to your email address. Please click on the link within 15 minutes in order to proceed." d) An OTP input field labeled as "Input OTP Code" is shown. e) Didn't receive the OTP on your email address? text field below f) "Click here to resend" link for request OTP g) Submit button | F5: PASSED
A6: =IF(B6<>"", "US-3-TC-" & TEXT(COUNTA($B$4:B7), "00"), "") -> US-3-TC-04 | B6: Verify that entering an invalid One-Time PIN (OTP) on the OTP verification page displays an error message. | C6: 1. User must be on the Sta. Rosa Payroll Portal. 2. User must be on the Login page. | D6: 1. Search Assessor office login 2. Login with registered email and password and checkbox of T&C. 3. Click Submit button 4. Check OTP Verification sent on email. 5. Put the invalid OTP on the Verification 6. Click submit or press enter | E6: The user is redirected to a confirmation screen displaying the following: a) "Assessor’s Office" header b) "One-Time Passcode c) A message is displayed: "An email verification has been sent to your email address. Please click on the link within 15 minutes in order to proceed." d) An OTP input field labeled as "Input OTP Code" is shown. e) Didn't receive the OTP on your email address? text field below f) "Click here to resend" link for request OTP g) Submit button | F6: PASSED
A7: =IF(B7<>"", "US-3-TC-" & TEXT(COUNTA($B$4:B8), "00"), "") -> US-3-TC-05 | B7: Verify that entering an expired One-Time PIN (OTP) after 15 minutes on the OTP verification page displays an error message indicating the OTP has expired. | C7: 1. User must be on the Sta. Rosa Payroll Portal. 2. User must be on the Login page. | D7: 1. Search Assessor office login 2. Login with registered email and password and checkbox of T&C. 3. Click Submit button 4. Check OTP Verification sent on email. 5. Put the expired OTP on the Verification 6. Click submit or press enter | E7: The user is redirected to a confirmation screen displaying the following: a) "Assessor’s Office" header b) "One-Time Passcode c) A message is displayed: "An email verification has been sent to your email address. Please click on the link within 15 minutes in order to proceed." d) An OTP input field labeled as "Input OTP Code" is shown. e) "Invalid verification code. Please try again." red text is shown below the field f) Didn't receive the OTP on your email address? text field below g) "Click here to resend" link for request OTP h) Submit button | F7: PASSED
A8: =IF(B8<>"", "US-3-TC-" & TEXT(COUNTA($B$4:B9), "00"), "") -> US-3-TC-06 | B8: Verify that a used OTP cannot be used again for verification on the OTP verification page. | C8: 1. User must be on the Sta. Rosa Payroll Portal. 2. User must be on the Login page. | D8: 1. Search Assessor office login 2. Login with registered email and password and checkbox of T&C. 3. Click Submit button 4. Click the Back to Home button | E8: Able to received an error message of "Invalid verification code. Please try again." | F8: PASSED
A9: =IF(B9<>"", "US-3-TC-" & TEXT(COUNTA($B$3:B10), "00"), "") -> US-3-TC-07 | B9: Verify that unable to request OTP if there is an existing OTP ongoing request. | C9: 1. User must be on the Sta. Rosa Payroll Portal. 2. User must be on the Login page. | D9: 1. Search Assessor office login 2. Login with registered email and password and checkbox of T&C. 3. Click Submit button 4. Click the Back to Home button | E9: The user is redirected to a confirmation screen displaying the following: a) "Assessor’s Office" header b) "One-Time Passcode c) A message is displayed: "An email verification has been sent to your email address. Please click on the link within 15 minutes in order to proceed." d) An OTP input field labeled as "Input OTP Code" is shown. e) "A One-Time PIN (OTP) has already been sent. Please wait 15 minutes before making another request." red text is shown below the field f) Didn't receive the OTP on your email address? text field below g) "Click here to resend" link for request OTP h) Submit button | F9: PASSED
A10: =IF(B10<>"", "US-3-TC-" & TEXT(COUNTA($B$3:B11), "00"), "")

Sheet PG-US-04
A1: PG-US-04 | B1: USER STORY: As a logged-in user of the Assessor’s Office portal, I want to access my profile, logout option, see a welcome message, and submit new requests easily, So that I can efficiently manage my account and services.
A2: Test Case ID | B2: Test Objective | C2: Preconditions | D2: Test Steps | E2: Expected Results | F2: Status | G2: Comments
A3: =IF(B3<>"", "US-4-TC-" & TEXT(COUNTA($B3:B$3), "00"), "") -> US-4-TC-01 | B3: Verify that clicking the "New Request" button redirects the user to the request of Certificate Application page. | C3: 1. User must be on the Sta. Rosa Payroll Portal. 2. User must be on the Login page. 3. User must be logged in 4. User must have successfully verified the One-Time PIN (OTP). 5. User must be on the New Request Page. | D3: 1. Search Assessor office login 2. Login with registered email and password and checkbox of T&C. 3. Have completed the OTP verification 4. Click the "New Request" button | E3: Certificate form should display all five checkbox options: a) Certificate of True Copy of Tax Declaration b) Transfer of Tax Declaration c) Certification of No-Property d) Certificate of Aggregate Landholdings e) Other Certifications - When user types into the "Type of Certificate" field, it should accept input with a popup guidance saying: “Put a comma between certificates. Example: Certificate A, Certificate B.” Claiming section should display two selectable options (radio buttons): a) Personal b) Authorized Representative c) "ID of Property Owner with 3 Signatures" w/ upload field button - field should allow drag-and-drop or file upload functionality. Accepted file types: .jpg, .png, .docx, .pdf Line separator Checkbox of I agree to the Terms & Condition of the City of the Sta Rosa Buttons (located the T&C): a) Save Changes — submits the form and saves the cretificate application b) Cancel — discards any changes and returns the user to the previous screen or dashboard | F3: PASSED | G3: "type of certificate" field changed to drop down. comma text no longer applicable. multi select from drop down doesnt seem to be allowed but primary function working
A4: =IF(B4<>"", "US-4-TC-" & TEXT(COUNTA($B$3:B4), "00"), "") -> US-4-TC-02 | B4: Verify that clicking the "Profile" link navigates the user to their profile details or account settings page. | C4: 1. User must be on the Sta. Rosa Payroll Portal. 2. User must be on the Login page. 3. User must be logged in 4. User must have successfully verified the One-Time PIN (OTP). 5. User must be on the New Request Page. | D4: 1. Search Assessor office login 2. Login with registered email and password and checkbox of T&C. 3. Have completed the OTP verification 4. Click the Profile link on the top right | E4: After the user is redirected to the Profile page, the screen should display the following layout and elements: Header: Assessor's Office Section: Profile a) First Name* — a text field is displayed below the label b) Middle Name — a text field is displayed below the label c) Last Name* — a text field is displayed below the label d) Date of Birth* — a text field is displayed below the label e) Contact Number* — a text field is displayed below the label f) E-mail Address — a text field is displayed below the label Line Separator Section: Password Update a) New Password* — a hashed password field is displayed below the label b) Confirm Password* — a hashed password field is displayed below the label Buttons (located below password fields): a) Save Changes — submits the form and saves the updated profile information b) Cancel — discards any changes and returns the user to the previous screen or dashboard | F4: PASSED
A5: =IF(B5<>"", "US-4-TC-" & TEXT(COUNTA($B$3:B5), "00"), "") -> US-4-TC-03 | B5: Verify that the user can successfully update the First Name without altering the password field. | C5: 1. User must be on the Sta. Rosa Payroll Portal. 2. User must be on the Login page. 3. User must be logged in 4. User must have successfully verified the One-Time PIN (OTP). 5. User must be on the New Request Page. | E5: After the user is redirected to the Profile page, the screen should display the following layout and elements: Header: Assessor's Office Section: Profile a) First Name* — a text field is displayed below the label b) Middle Name — a text field is displayed below the label c) Last Name* — a text field is displayed below the label d) Date of Birth* — a text field is displayed below the label e) Contact Number* — a text field is displayed below the label f) E-mail Address — a text field is displayed below the label Line Separator Section: Password Update a) New Password* — a hashed password field is displayed below the label b) Confirm Password* — a hashed password field is displayed below the label Buttons (located below password fields): a) Save Changes — submits the form and saves the updated profile information b) Cancel — discards any changes and returns the user to the previous screen or dashboard | F5: PASSED
A6: =IF(B6<>"", "US-4-TC-" & TEXT(COUNTA($B$3:B6), "00"), "") -> US-4-TC-04 | B6: Verify that the user can update the Middle Name without modifying the password. | C6: 1. User must be on the Sta. Rosa Payroll Portal. 2. User must be on the Login page. 3. User must be logged in 4. User must have successfully verified the One-Time PIN (OTP). 5. User must be on the New Request Page. | D6: 1. Search Assessor office login 2. Login with registered email and password and checkbox of T&C. 3. Have completed the OTP verification 4. Click the Profile link on the top right 5. Update the Middle Name field. 6. Leave the Password field blank. 7. Click the Save Changes button. 8. Confirm that the Middle Name is saved successfully without a password update. | E6: After the user is redirected to the Profile page, the screen should display the following layout and elements: Header: Assessor's Office Section: Profile a) First Name* — a text field is displayed below the label b) Middle Name — a text field is displayed below the label c) Last Name* — a text field is displayed below the label d) Date of Birth* — a text field is displayed below the label e) Contact Number* — a text field is displayed below the label f) E-mail Address — a text field is displayed below the label Line Separator Section: Password Update a) New Password* — a hashed password field is displayed below the label b) Confirm Password* — a hashed password field is displayed below the label Buttons (located below password fields): a) Save Changes — submits the form and saves the updated profile information b) Cancel — discards any changes and returns the user to the previous screen or dashboard | F6: PASSED
A7: =IF(B7<>"", "US-4-TC-" & TEXT(COUNTA($B$3:B7), "00"), "") -> US-4-TC-05 | B7: Verify that the user can update the Last Name independently of the password field. | C7: 1. User must be on the Sta. Rosa Payroll Portal. 2. User must be on the Login page. 3. User must be logged in 4. User must have successfully verified the One-Time PIN (OTP). 5. User must be on the New Request Page. | D7: 1. Search Assessor office login 2. Login with registered email and password and checkbox of T&C. 3. Have completed the OTP verification 4. Click the Profile link on the top right 5. Modify the Last Name field. 6. Leave the Password field empty. 7. Click the Save Changes button 8. Ensure that the Last Name change is reflected without altering the password. | E7: After the user is redirected to the Profile page, the screen should display the following layout and elements: Header: Assessor's Office Section: Profile a) First Name* — a text field is displayed below the label b) Middle Name — a text field is displayed below the label c) Last Name* — a text field is displayed below the label d) Date of Birth* — a text field is displayed below the label e) Contact Number* — a text field is displayed below the label f) E-mail Address — a text field is displayed below the label Line Separator Section: Password Update a) New Password* — a hashed password field is displayed below the label b) Confirm Password* — a hashed password field is displayed below the label Buttons (located below password fields): a) Save Changes — submits the form and saves the updated profile information b) Cancel — discards any changes and returns the user to the previous screen or dashboard | F7: PASSED
A8: =IF(B8<>"", "US-4-TC-" & TEXT(COUNTA($B$3:B8), "00"), "") -> US-4-TC-06 | B8: Confirm that Date of Birth can be edited and saved without updating the password. | C8: 1. User must be on the Sta. Rosa Payroll Portal. 2. User must be on the Login page. 3. User must be logged in 4. User must have successfully verified the One-Time PIN (OTP). 5. User must be on the New Request Page. | D8: 1. Search Assessor office login 2. Login with registered email and password and checkbox of T&C. 3. Have completed the OTP verification 4. Click the Profile link on the top right 5. Edit the Date of Birth field. 6. Leave the Password field blank. 7. Click the Save Changes button 8. Validate that the Date of Birth is updated successfully without requiring password input. | E8: After the user is redirected to the Profile page, the screen should display the following layout and elements: Header: Assessor's Office Section: Profile a) First Name* — a text field is displayed below the label b) Middle Name — a text field is displayed below the label c) Last Name* — a text field is displayed below the label d) Date of Birth* — a text field is displayed below the label e) Contact Number* — a text field is displayed below the label f) E-mail Address — a text field is displayed below the label Line Separator Section: Password Update a) New Password* — a hashed password field is displayed below the label b) Confirm Password* — a hashed password field is displayed below the label Buttons (located below password fields): a) Save Changes — submits the form and saves the updated profile information b) Cancel — discards any changes and returns the user to the previous screen or dashboard | F8: PASSED | G8: allows me to select future dates past current date
A9: =IF(B9<>"", "US-4-TC-" & TEXT(COUNTA($B$3:B9), "00"), "") -> US-4-TC-07 | B9: Verify that the user can update the Contact Number without needing to input a new password. | C9: 1. User must be on the Sta. Rosa Payroll Portal. 2. User must be on the Login page. 3. User must be logged in 4. User must have successfully verified the One-Time PIN (OTP). 5. User must be on the New Request Page. | D9: 1. Search Assessor office login 2. Login with registered email and password and checkbox of T&C. 3. Have completed the OTP verification 4. Click the Profile link on the top right 5. Update the Contact Number field. 6. Leave the Password field empty. 7. Click the Save Changes button 8. Confirm that the new Contact Number is saved successfully without changing the password. | E9: After the user is redirected to the Profile page, the screen should display the following layout and elements: Header: Assessor's Office Section: Profile a) First Name* — a text field is displayed below the label b) Middle Name — a text field is displayed below the label c) Last Name* — a text field is displayed below the label d) Date of Birth* — a text field is displayed below the label e) Contact Number* — a text field is displayed below the label f) E-mail Address — a text field is displayed below the label Line Separator Section: Password Update a) New Password* — a hashed password field is displayed below the label b) Confirm Password* — a hashed password field is displayed below the label Buttons (located below password fields): a) Save Changes — submits the form and saves the updated profile information b) Cancel — discards any changes and returns the user to the previous screen or dashboard | F9: PASSED
A10: =IF(B10<>"", "US-4-TC-" & TEXT(COUNTA($B$3:B10), "00"), "") -> US-4-TC-08 | B10: Verify that the user can change their Email Address while leaving the password field blank. | C10: 1. User must be on the Sta. Rosa Payroll Portal. 2. User must be on the Login page. 3. User must be logged in 4. User must have successfully verified the One-Time PIN (OTP). 5. User must be on the New Request Page. | D10: 1. Search Assessor office login 2. Login with registered email and password and checkbox of T&C. 3. Have completed the OTP verification 4. Click the Profile link on the top right 5. Edit the Email Address field. 6. Leave the Password field blank. 7. Click the Save Changes button 8. Verify that the Email Address is updated and saved successfully without entering a password. | E10: After the user is redirected to the Profile page, the screen should display the following layout and elements: Header: Assessor's Office Section: Profile a) First Name* — a text field is displayed below the label b) Middle Name — a text field is displayed below the label c) Last Name* — a text field is displayed below the label d) Date of Birth* — a text field is displayed below the label e) Contact Number* — a text field is displayed below the label f) E-mail Address — a text field is displayed below the label Line Separator Section: Password Update a) New Password* — a hashed password field is displayed below the label b) Confirm Password* — a hashed password field is displayed below the label Buttons (located below password fields): a) Save Changes — submits the form and saves the updated profile information b) Cancel — discards any changes and returns the user to the previous screen or dashboard | F10: PASSED
A11: =IF(B11<>"", "US-4-TC-" & TEXT(COUNTA($B$3:B11), "00"), "") -> US-4-TC-09 | B11: Verify that clicking the "Logout" link logs the user out and redirects them to the login page. | C11: 1. User must be on the Sta. Rosa Payroll Portal. 2. User must be on the Login page. 3. User must be logged in 4. User must have successfully verified the One-Time PIN (OTP). 5. User must be on the New Request Page. | D11: 1. Search Assessor office login 2. Login with registered email and password and checkbox of T&C. 3. Have completed the OTP verification 4. Click the Logout link on the top right | E11: The user will be directed to Login Page of Assessor Office Portal. The Assessor Office Login Page consists of the following elements: a) Email address field b) Password field c) Terms & Conditions checkbox d) Submit button e) Forgot Password link f) ""New? Sign up"" button - If the Terms & Conditions checkbox is not checked, a validation message appears: "Please accept the Terms & Conditions to proceed." | F11: PASSED

Sheet PG-US-05
A1: PG-US-05 | B1: USER STORY: As a property owner, I want to apply for a Certificate of True Copy of Tax Declaration So that I can process my property documentation And have it claimed as Personal
A2: Test Case ID | B2: Test Objective | C2: Preconditions | D2: Test Steps | E2: Expected Results | F2: Status | G2: Comments
A3: =IF(B3<>"", "US-5-TC-" & TEXT(COUNTA($B3:B$3), "00"), "") -> US-5-TC-01 | B3: Verify that the user is able to select both the "Certificate of True Copy of Tax" checkbox under the Type of Certificate section. | C3: 1. User must be on the Sta. Rosa Payroll Portal. 2. User must be on the Login page. 3. User must be logged in the Assessor's Office portal 4. User must be on the request page of Certificate of Application | D3: 1. Search Assessor office login 2. Login with registered email and password and checkbox of T&C. 3. Click Submit button 4. Check OTP Verification sent on email. 5. Put the OTP on the Verification 6. Click the "New Request" button 7. Click the Click the Transfer of Tax Declaration under Type of Certificate 8. Chose the Authorized Representative option under Claiming | E3: Type of Certificate: The user successfully selects both of the following checkboxes: a) Transfer of Tax Declaration Claiming Method: -- The user selects the Personal radio button. ID of Property Owner with 3 Signatures: - The required document is successfully uploaded via the drag-and-drop or upload file field. | F3: PASSED
A4: =IF(B4<>"", "US-5-TC-" & TEXT(COUNTA($B$3:B4), "00"), "") -> US-5-TC-02 | B4: Verify that the user is able to select the “Personal” radio button under the Claiming section. | C4: 1. User must be on the Sta. Rosa Payroll Portal. 2. User must be on the Login page. 3. User must be logged in the Assessor's Office portal 4. User must be on the request page of Certificate of Application | D4: 1. Search Assessor office login 2. Login with registered email and password and checkbox of T&C. 3. Click Submit button 4. Check OTP Verification sent on email. 5. Put the OTP on the Verification 6. Click the "New Request" button 7. Click the Click the Transfer of Tax Declaration under Type of Certificate 8. Chose the Authorized Representative option under Claiming | E4: Type of Certificate: The user successfully selects both of the following checkboxes: a) Transfer of Tax Declaration Claiming Method: -- The user selects the Personal radio button. ID of Property Owner with 3 Signatures: - The required document is successfully uploaded via the drag-and-drop or upload file field. | F4: PASSED
A5: =IF(B5<>"", "US-5-TC-" & TEXT(COUNTA($B$3:B5), "00"), "") -> US-5-TC-03 | B5: Verify that the system accepts and successfully uploads a valid file (.jpg, .png, .docx, or .pdf) for the ID of Property Owner with 3 Signatures | C5: 1. User must be on the Sta. Rosa Payroll Portal. 2. User must be on the Login page. 3. User must be logged in the Assessor's Office portal 4. User must be on the request page of Certificate of Application | D5: 1. Search Assessor office login 2. Login with registered email and password and checkbox of T&C. 3. Click Submit button 4. Check OTP Verification sent on email. 5. Put the OTP on the Verification 6. Click the "New Request" button 7. Click the Click the Transfer of Tax Declaration under Type of Certificate 8. Chose the Authorized Representative option under Claiming | E5: Type of Certificate: The user successfully selects both of the following checkboxes: a) Transfer of Tax Declaration Claiming Method: -- The user selects the Personal radio button. ID of Property Owner with 3 Signatures: - The required document is successfully uploaded via the drag-and-drop or upload file field. | F5: PASSED
A6: =IF(B6<>"", "US-5-TC-" & TEXT(COUNTA($B$3:B6), "00"), "") -> US-5-TC-04 | B6: Verify that when the user clicks the information icon beside 'ID of Property Owner with 3 Signatures ', the system displays the Certificate Requirements. | C6: 1. User must be on the Sta. Rosa Payroll Portal. 2. User must be on the Login page. 3. User must be logged in the Assessor's Office portal 4. User must be on the request page of Certificate of Application | D6: 1. Search Assessor office login 2. Login with registered email and password and checkbox of T&C. 3. Click Submit button 4. Check OTP Verification sent on email. 5. Put the OTP on the Verification 6. Click the "New Request" button 7. Click the Click the Transfer of Tax Declaration under Type of Certificate 8. Chose the Authorized Representative option under Claiming | E6: When the user clicks the information icon beside the “ID of Representative with 3 Signatures” field, the system must display a pop-up window containing the complete list of Certificate Requirements. The pop-up must include the following categorized details: Certificate Requirements For Certificate of True Copy of Tax Declaration / Certificate of Aggregate Landholdings / Certification of No-Property / Other Certifications: • ID of Property Owner with three (3) Signatures • Original Copy of Contract of Lease • Original Copy of Deed of Absolute Sale (DOAS) • Original Copy of Contract to Sell • Proof of Ownership • If Company / Bank Developer: Secretary’s Certificate and one (1) employee ID • If Loan Mortgage: Photocopy of Loan Agreement For Transfer of Tax Declaration: • ID of Property Owner with three (3) Signatures • Certified True Copy of Title • Xerox Copy of Deed of Sale / Donation / Extra Judicial Settlement • Xerox Copy of Real Property Tax Receipt or Tax Clearance • Xerox Copy of Transfer Tax Receipt or Certification of Transfer Tax • Xerox Copy of C.A.R (B.I.R) • Receipt from RD for New Title • For subdivided lots: Copy of Subdivision Plan • For Canceled Titles: Certified Canceled Title • For Foreclosed Lots: Certification of Sale and Affidavit of Consolidation of Ownership Additional Documents for Authorized Representative • ID of Authorized Representative with three (3) Signatures • Original Copy of Authorization Letter • Original Copy of Special Power of Attorney (SPA) | F6: PASSED
A7: =IF(B7<>"", "US-5-TC-" & TEXT(COUNTA($B$3:B7), "00"), "") -> US-5-TC-05 | B7: Verify that the system prevents form submission and displays a validation error when the ID of Property Owner with 3 Signatures upload field is left blank. | C7: 1. User must be on the Sta. Rosa Payroll Portal. 2. User must be on the Login page. 3. User must be logged in the Assessor's Office portal 4. User must be on the request page of Certificate of Application | D7: 1. Search Assessor office login 2. Login with registered email and password and checkbox of T&C. 3. Click Submit button 4. Check OTP Verification sent on email. 5. Put the OTP on the Verification 6. Click the "New Request" button 7. Click the Click the Transfer of Tax Declaration under Type of Certificate 8. Chose the Authorized Representative option under Claiming | E7: Authorized Representative Requirements These are the required documents for the Authorized Representative. All fields are mandatory, and the system will not accept submission unless valid documents are uploaded. Valid file types include .jpg, .png, .docx, or .pdf: • ID of Representative with 3 Signatures • Supported file types: jpg, png, docx, or pdf only • File upload field with an Upload File button Special Power of Attorney (SPA) • Supported file types: jpg, png, docx, or pdf only • File upload field with an Upload File button Authorization Letter • Supported file types: jpg, png, docx, or pdf only • File upload field with an Upload File button Authorized Representative Requirements Validation: • If the file upload is left blank, the system triggers a required field validation error with the message: “Please upload an ID of Representative with 3 Signatures document in .jpg, .png, .docx, or .pdf format only.” • The system must block submission until a valid file is uploaded. | F7: PASSED
A8: =IF(B8<>"", "US-5-TC-" & TEXT(COUNTA($B$3:B8), "00"), "") -> US-5-TC-06 | B8: Verify that the system rejects and displays an error message when an unsupported file type (e.g., .exe, .zip) is uploaded to theID of Property Owner with 3 Signatures field. | C8: 1. User must be on the Sta. Rosa Payroll Portal. 2. User must be on the Login page. 3. User must be logged in the Assessor's Office portal 4. User must be on the request page of Certificate of Application | D8: 1. Search Assessor office login 2. Login with registered email and password and checkbox of T&C. 3. Click Submit button 4. Check OTP Verification sent on email. 5. Put the OTP on the Verification 6. Click the "New Request" button 7. Click the Click the Transfer of Tax Declaration under Type of Certificate 8. Chose the Authorized Representative option under Claiming | E8: The system rejects the unsupported file upload. An error message is displayed: “Please upload an ID of Representative with 3 Signatures document in .jpg, .png, .docx, or .pdf format only.” The invalid file is not accepted or saved. | F8: PASSED
A9: =IF(B9<>"", "US-5-TC-" & TEXT(COUNTA($B$3:B9), "00"), "") -> US-5-TC-07 | B9: Verify that the uploaded "ID of Property Owner with three (3) Signatures" file can be removed by clicking the “X” button located beside the uploaded file . | C9: 1. User must be on the Sta. Rosa Payroll Portal. 2. User must be on the Login page. 3. User must be logged in the Assessor's Office portal 4. User must be on the request page of Certificate of Application | D9: 1. Search Assessor office login 2. Login with registered email and password and checkbox of T&C. 3. Click Submit button 4. Check OTP Verification sent on email. 5. Put the OTP on the Verification 6. Click the "New Request" button 7. Click the Click the Transfer of Tax Declaration under Type of Certificate 8. Chose the Authorized Representative option under Claiming | E9: The uploaded "ID of Property Owner with three (3) Signatures" file shall be successfully removed from the form when the user clicks the “X” button located beside the uploaded file, and the upload field shall be cleared to allow a new file to be uploaded. | F9: PASSED
A10: =IF(B10<>"", "US-5-TC-" & TEXT(COUNTA($B$3:B10), "00"), "") -> US-5-TC-08 | B10: Verify that only one file can be uploaded for the "ID of Property Owner with three (3) Signatures" field and that the system processes only the uploaded file when applying | C10: 1. User must be on the Sta. Rosa Payroll Portal. 2. User must be on the Login page. 3. User must be logged in the Assessor's Office portal 4. User must be on the request page of Certificate of Application | D10: 1. Search Assessor office login 2. Login with registered email and password and checkbox of T&C. 3. Click Submit button 4. Check OTP Verification sent on email. 5. Put the OTP on the Verification 6. Click the "New Request" button 7. Click the Click the Transfer of Tax Declaration under Type of Certificate 8. Chose the Authorized Representative option under Claiming | E10: The system shall allow uploading only one file for the "ID of Property Owner with three (3) Signatures" field. If a new file is uploaded, it shall replace the previously uploaded file. The system shall process only the currently uploaded file during the application submission. | F10: PASSED
A11: =IF(B11<>"", "US-5-TC-" & TEXT(COUNTA($B$3:B11), "00"), "") -> US-5-TC-09 | B11: Verify that uploading a new file for the "ID of Property Owner with three (3) Signatures" field replaces the previously uploaded file | C11: 1. User must be on the Sta. Rosa Payroll Portal. 2. User must be on the Login page. 3. User must be logged in the Assessor's Office portal 4. User must be on the request page of Certificate of Application | D11: 1. Search Assessor office login 2. Login with registered email and password and checkbox of T&C. 3. Click Submit button 4. Check OTP Verification sent on email. 5. Put the OTP on the Verification 6. Click the "New Request" button 7. Click the Click the Transfer of Tax Declaration under Type of Certificate 8. Chose the Authorized Representative option under Claiming | E11: When a new file is uploaded for the "ID of Property Owner with three (3) Signatures" field, the system shall replace the previously uploaded file with the new one, displaying only the latest uploaded file in the upload section. | F11: PASSED
A12: =IF(B12<>"", "US-5-TC-" & TEXT(COUNTA($B$3:B12), "00"), "") -> US-5-TC-10 | B12: Verify that the form prevents submission when the uploaded file for ID of Property Owner with three (3) Signatures is blank, corrupted, or unreadable | C12: 1. User must be on the Sta. Rosa Payroll Portal. 2. User must be on the Login page. 3. User must be logged in the Assessor's Office portal 4. User must be on the request page of Certificate of Application | D12: 1. Search Assessor office login 2. Login with registered email and password and checkbox of T&C. 3. Click Submit button 4. Check OTP Verification sent on email. 5. Put the OTP on the Verification 6. Click the "New Request" button 7. Click the Click the Transfer of Tax Declaration under Type of Certificate 8. Chose the Authorized Representative option under Claiming | E12: The form shall prevent submission if the uploaded file for the “ID of Property Owner with three (3) Signatures” is blank, corrupted, or unreadable. A clear validation message or notification shall be displayed near the upload field or as a general alert, stating: 1.) “The ID of Property Owner with three (3) Signatures is required. Please upload a jpg, png, docx or pdf files only.” 2.) The user shall remain on the current form page with all previously entered data preserved, except for the missing or invalid file. 3.) The system shall block form submission until a valid and readable file in the accepted formats (.jpg, .png, .docx, .pdf) is successfully uploaded for this required field. | F12: PASSED
A13: =IF(B13<>"", "US-5-TC-" & TEXT(COUNTA($B$3:B13), "00"), "") -> US-5-TC-11 | B13: Verify that the system accepts and successfully uploads a valid file (.jpg, .png, .docx, or .pdf) for the Contract of Lease field on the Certificate Requirements. | C13: 1. User must be on the Sta. Rosa Payroll Portal. 2. User must be on the Login page. 3. User must be logged in the Assessor's Office portal 4. User must be on the request page of Certificate of Application | D13: 1. Search for the Assessor Office login page. 2. Log in using a registered email and password, and check the Terms & Conditions checkbox. 3. Click the Submit button. 4. Check the OTP verification sent to the registered email. 5. Enter the OTP in the verification field. 6. Click the New Request button. 7. Select Certificate of True Copy of Tax Declaration under Type of Certificate. 8. Select Transfer of Tax Declaration under Type of Certificate. 9. Choose the Personal option under Claiming. 10. In the Contract of Lease upload field, click Upload File, then select a valid .jpg, .png, .docx, or .pdf file. 11. Click Submit. | E13: These are the following details for the certification requirements. All fields are mandatory, and the system will not accept submission without uploading the required documents. Valid file types include .jpg, .png, .docx, or .pdf: Certification Requirements Note: All fields are mandatory. The system will not accept the submission if a document is not uploaded. Hover over the information icon to see the list of Valid IDs. (information icon) a) Contract of Lease jpg, png, docx or pdf files only File Upload File button b) Deed of Absolute Sale (DOAS) jpg, png, docx or pdf files only File Upload File button c) Proof of Ownership jpg, png, docx or pdf files only File Upload File button d) Contract to Sell jpg, png, docx or pdf files only File Upload File button Contract of Lease Field: • Accepts only valid file types: .jpg, .png, .docx, .pdf. | F13: PASSED
A14: =IF(B14<>"", "US-5-TC-" & TEXT(COUNTA($B$3:B14), "00"), "") -> US-5-TC-12 | B14: Verify that clicking the 'X' button in the upload field successfully removes the selected file on the Contract of Lease upload field. | C14: 1. User must be on the Sta. Rosa Payroll Portal. 2. User must be on the Login page. 3. User must be logged in the Assessor's Office portal 4. User must be on the request page of Certificate of Application | D14: 1. Search for the Assessor Office login page. 2. Log in using a registered email and password, and check the Terms & Conditions checkbox. 3. Click the Submit button. 4. Check the OTP verification sent to the registered email. 5. Enter the OTP in the verification field. 6. Click the New Request button. 7. Select Certificate of True Copy of Tax Declaration under Type of Certificate. 8. Select Transfer of Tax Declaration under Type of Certificate. 9. Choose the Personal option under Claiming. 10. In the Contract of Lease upload field, click Upload File, then select a valid .jpg, .png, .docx, or .pdf file. 11. Click Submit. | E14: These are the following details for the certification requirements. All fields are mandatory, and the system will not accept submission without uploading the required documents. Valid file types include .jpg, .png, .docx, or .pdf: Certification Requirements Note: All fields are mandatory. The system will not accept the submission if a document is not uploaded. Hover over the information icon to see the list of Valid IDs. (information icon) a) Contract of Lease jpg, png, docx or pdf files only File Upload File button b) Deed of Absolute Sale (DOAS) jpg, png, docx or pdf files only File Upload File button c) Proof of Ownership jpg, png, docx or pdf files only File Upload File button d) Contract to Sell jpg, png, docx or pdf files only File Upload File button Contract of Lease Field: • Accepts only valid file types: .jpg, .png, .docx, .pdf. | F14: PASSED
A15: =IF(B15<>"", "US-5-TC-" & TEXT(COUNTA($B$3:B15), "00"), "") -> US-5-TC-13 | B15: Verify that the system prevents form submission and displays a validation error when the Contract of Lease upload field is left blank on the Certificate Requirements. | C15: 1. User must be on the Sta. Rosa Payroll Portal. 2. User must be on the Login page. 3. User must be logged in the Assessor's Office portal 4. User must be on the request page of Certificate of Application | D15: 1. Search for the Assessor Office login page. 2. Log in using a registered email and password, and check the Terms & Conditions checkbox. 3. Click the Submit button. 4. Check the OTP verification sent to the registered email. 5. Enter the OTP in the verification field. 6. Click the New Request button. 7. Select Certificate of True Copy of Tax Declaration under Type of Certificate. 8. Select Transfer of Tax Declaration under Type of Certificate. 9. Choose the Personal option under Claiming. 10. Leave the “Contract of Lease” field empty. 11. Fill out other required document fields with valid files. 12. Click the "Submit" button. | E15: These are the following details for the certification requirements. All fields are mandatory, and the system will not accept submission without uploading the required documents. Valid file types include .jpg, .png, .docx, or .pdf: Certification Requirements Note: All fields are mandatory. The system will not accept the submission if a document is not uploaded. Hover over the information icon to see the list of Valid IDs. (information icon) a) Contract of Lease jpg, png, docx or pdf files only File Upload File button b) Deed of Absolute Sale (DOAS) jpg, png, docx or pdf files only File Upload File button c) Proof of Ownership jpg, png, docx or pdf files only File Upload File button d) Contract to Sell jpg, png, docx or pdf files only File Upload File button Contract of Lease Field: • Leaving this field blank prevents form submission and shows a required field validation error "Please upload a Contract of Lease document in .jpg, .png, .docx, or .pdf format only." and blocks submission. | F15: PASSED
... A29: =IF(B29<>"", "US-5-TC-" & TEXT(COUNTA($B$3:B29), "00"), "") -> US-5-TC-27 | B29: Verify that selecting “Yes” for “Are you a Company/Bank Developer?” displays the "Secretary’s Certificate and one (1) employee ID" | C29: 1. User must be on the Sta. Rosa Payroll Portal. 2. User must be on the Login page. 3. User must be logged in the Assessor's Office portal 4. User must be on the request page of Certificate of Application | D29: 1. Search for the Assessor Office login page. 2. Log in using a registered email and password, and check the Terms & Conditions checkbox. 3. Click the Submit button. 4. Check the OTP verification sent to the registered email. 5. Enter the OTP in the verification field. 6. Click the New Request button. 7. Select Certificate of True Copy of Tax Declaration under Type of Certificate. 8. Select Transfer of Tax Declaration under Type of Certificate. 9. Choose the Personal option under Claiming. 10. Upload a valid file (.jpg, .png, .docx, or .pdf) to the following fields: • Contract of Lease • Deed of Absolute Sale (DOAS) • Proof of Ownership • Contract to Sell 11. Select Yes for “Are you a Company/Bank Developer?” 12. Click the Upload button for: • Secretary’s Certificate • Employee ID 13. Fill out all other required fields 14. Click the Submit button. | E29: When the user selects “Yes” for the question “Are you a Company/Bank Developer?”, the system should: A new section labeled “Secretary’s Certificate and one (1) employee ID” should appear immediately without requiring a page refresh or redirection. Each upload field must contain: • A File label identifying the required document. • A note under or beside each field: "jpg, png, docx or pdf files only" • A button or area labeled “Upload File” to upload the supported file. | F29: PASSED
A30: =IF(B30<>"", "US-5-TC-" & TEXT(COUNTA($B$3:B30), "00"), "") -> US-5-TC-28 | B30: Verify that selecting 'Yes' for 'Are you a Company/Bank Developer?' allows successful upload of valid file types (e.g., .png, .jpg, .docx, .pdf) in the 'Secretary’s Certificate and one (1) employee ID' upload field. | F30: PASSED
A31: =IF(B31<>"", "US-5-TC-" & TEXT(COUNTA($B$3:B31), "00"), "") -> US-5-TC-29 | B31: Verify that the form prevents submission when “Are you a Company/Bank Developer?” is Yes but "Secretary’s Certificate and one (1) employee ID" files are not uploaded. | C31: 1. User must be on the Sta. Rosa Payroll Portal. 2. User must be on the Login page. 3. User must be logged in the Assessor's Office portal 4. User must be on the request page of Certificate of Application | D31: 1. Search for the Assessor Office login page. 2. Log in using a registered email and password, and check the Terms & Conditions checkbox. 3. Click the Submit button. 4. Check the OTP verification sent to the registered email. 5. Enter the OTP in the verification field. 6. Click the New Request button. 7. Select Certificate of True Copy of Tax Declaration under Type of Certificate. 8. Select Transfer of Tax Declaration under Type of Certificate. 9. Choose the Personal option under Claiming. 10. Upload a valid file (.jpg, .png, .docx, or .pdf) to the following fields: • Contract of Lease • Deed of Absolute Sale (DOAS) • Proof of Ownership • Contract to Sell 11. Select Yes for “Are you a Company/Bank Developer?” 12. Do not upload any files to: • Secretary’s Certificate • Employee ID 13. Fill out all other required fields. 14. Click Submit. | E31: When the user selects "Yes" for the "Are you a Company/Bank Developer?" question and does not upload the required files under the "Secretary’s Certificate and one (1) employee ID" section: A new section labeled “Secretary’s Certificate and one (1) employee ID” should immediately appear on the form without requiring a page reload. Each upload field must contain: • A File label identifying the required document. • A note under or beside each field: "jpg, png, docx or pdf files only" • A button or area labeled “Upload File” to upload the supported file. Upon clicking Submit, the system should detect that the Secretary’s Certificate and/or Employee ID files have not been uploaded. The form submission must be blocked. A clear and specific error message should be displayed near each empty file upload field, such as: “Please upload the Secretary’s Certificate and Employee ID.” | F31: PASSED
A32: =IF(B32<>"", "US-5-TC-" & TEXT(COUNTA($B$3:B32), "00"), "") -> US-5-TC-30 | B32: Verify that clicking the 'X' button in the upload field successfully removes the selected file on the Secretary's Certificate and one (1) employee ID upload field. | C32: 1. User must be on the Sta. Rosa Payroll Portal. 2. User must be on the Login page. 3. User must be logged in the Assessor's Office portal 4. User must be on the request page of Certificate of Application | D32: 1. Search for the Assessor Office login page. 2. Log in using a registered email and password, and check the Terms & Conditions checkbox. 3. Click the Submit button. 4. Check the OTP verification sent to the registered email. 5. Enter the OTP in the verification field. 6. Click the New Request button. 7. Select Certificate of True Copy of Tax Declaration under Type of Certificate. 8. Select Transfer of Tax Declaration under Type of Certificate. 9. Choose the Personal option under Claiming. 10. Upload a valid file (.jpg, .png, .docx, or .pdf) to the following fields: • Contract of Lease • Deed of Absolute Sale (DOAS) • Proof of Ownership • Contract to Sell 11. Select Yes for “Are you a Company/Bank Developer?” 12. Do not upload any files to: • Secretary’s Certificate • Employee ID 13. Fill out all other required fields. 14. Click Submit. | E32: When the user selects "Yes" for the "Are you a Company/Bank Developer?" question and does not upload the required files under the "Secretary’s Certificate and one (1) employee ID" section: A new section labeled “Secretary’s Certificate and one (1) employee ID” should immediately appear on the form without requiring a page reload. Each upload field must contain: • A File label identifying the required document. • A note under or beside each field: "jpg, png, docx or pdf files only" • A button or area labeled “Upload File” to upload the supported file. Upon clicking Submit, the system should detect that the Secretary’s Certificate and/or Employee ID files have not been uploaded. The form submission must be blocked. A clear and specific error message should be displayed near each empty file upload field, such as: “Please upload the Secretary’s Certificate and Employee ID.” | F32: PASSED
A33: =IF(B33<>"", "US-5-TC-" & TEXT(COUNTA($B$3:B33), "00"), "") -> US-5-TC-31 | B33: Verify that the system rejects unsupported file types for “Are you a Company/Bank Developer?” under "Secretary’s Certificate and one (1) employee ID" uploads. | C33: 1. User must be on the Sta. Rosa Payroll Portal. 2. User must be on the Login page. 3. User must be logged in the Assessor's Office portal 4. User must be on the request page of Certificate of Application | D33: 1. Search for the Assessor Office login page. 2. Log in using a registered email and password, and check the Terms & Conditions checkbox. 3. Click the Submit button. 4. Check the OTP verification sent to the registered email. 5. Enter the OTP in the verification field. 6. Click the New Request button. 7. Select Certificate of True Copy of Tax Declaration under Type of Certificate. 8. Select Transfer of Tax Declaration under Type of Certificate. 9. Choose the Personal option under Claiming. 10. Upload a valid file (.jpg, .png, .docx, or .pdf) to the following fields: • Contract of Lease • Deed of Absolute Sale (DOAS) • Proof of Ownership • Contract to Sell 11. Select Yes for “Are you a Company/Bank Developer?” 12. Upload unsupported file types (e.g., .exe, .zip, .js) to: • Secretary’s Certificate • Employee ID 13. Complete other required fields. 14. Click Submit. | E33: When the user selects "Yes" for the "Are you a Company/Bank Developer?" question and does not upload the required files under the "Secretary’s Certificate and one (1) employee ID" section: A new section labeled “Secretary’s Certificate and one (1) employee ID” should immediately appear on the form without requiring a page reload. Each upload field must contain: • A File label identifying the required document. • A note under or beside each field: "jpg, png, docx or pdf files only" • A button or area labeled “Upload File” to upload the supported file. If the user tries to upload an unsupported file format (e.g., .exe, .txt, .zip), an immediate inline warning should appear: • The file must be rejected and not attached to the form. | F33: PASSED
A34: =IF(B34<>"", "US-5-TC-" & TEXT(COUNTA($B$3:B34), "00"), "") -> US-5-TC-32 | B34: Verify that the user is able to select “No” for “Are you a Company/Bank Developer?” | C34: 1. User must be on the Sta. Rosa Payroll Portal. 2. User must be on the Login page. 3. User must be logged in the Assessor's Office portal 4. User must be on the request page of Certificate of Application | D34: 1. Search for the Assessor Office login page. 2. Log in using a registered email and password, and check the Terms & Conditions checkbox. 3. Click the Submit button. 4. Check the OTP verification sent to the registered email. 5. Enter the OTP in the verification field. 6. Click the New Request button. 7. Select Certificate of True Copy of Tax Declaration under Type of Certificate. 8. Select Transfer of Tax Declaration under Type of Certificate. 9. Choose the Personal option under Claiming. 10. Upload a valid file (.jpg, .png, .docx, or .pdf) to the following fields: • Contract of Lease • Deed of Absolute Sale (DOAS) • Proof of Ownership • Contract to Sell 11. Select No for “Are you a Company/Bank Developer?” 12. Fill out all remaining required fields. 13. Click Submit. | E34: When the user clicks or selects the “No” option for the question “Are you a Company/Bank Developer?”: • The system should register the selection without delay or requiring a page reload. • The selection should be visually confirmed (e.g., radio button becomes filled or highlighted). • The “Secretary’s Certificate and one (1) employee ID” section should not appear at all if it hasn't already been shown. | F34: PASSED
A35: =IF(B35<>"", "US-5-TC-" & TEXT(COUNTA($B$3:B35), "00"), "") -> US-5-TC-33 | B35: Verify that selecting “Yes” for “Is this a Loan Mortgage?” displays the "Photocopy of Loan Agreement" | C35: 1. User must be on the Sta. Rosa Payroll Portal. 2. User must be on the Login page. 3. User must be logged in the Assessor's Office portal 4. User must be on the request page of Certificate of Application | D35: 1. Search for the Assessor Office login page. 2. Log in using a registered email and password, and check the Terms & Conditions checkbox. 3. Click the Submit button. 4. Check the OTP verification sent to the registered email. 5. Enter the OTP in the verification field. 6. Click the New Request button. 7. Select Certificate of True Copy of Tax Declaration under Type of Certificate. 8. Select Transfer of Tax Declaration under Type of Certificate. 9. Choose the Personal option under Claiming. 10. Upload a valid file (.jpg, .png, .docx, or .pdf) to the following fields: • Contract of Lease • Deed of Absolute Sale (DOAS) • Proof of Ownership • Contract to Sell 11. Select Yes for “Are you a Company/Bank Developer?” 12. On the upload button for "Secretary’s Certificate and one (1) employee ID", the user must upload files for both: • Secretary’s Certificate • Employee ID 13. Select Yes for “Is this a Loan Mortgage?" 14. On the upload button for "Photocopy of Loan Agreement", the user must upload a valid file to proceed with the form submission. 15. Fill out all other required fields 16. Click the Submit button. | E35: When the user selects “Yes” for the question “Is this a Loan Mortgage?”, the system should: A new section labeled “Photocopy of Loan Agreement” should appear immediately without requiring a page refresh or redirection. Each upload field must contain: • A File label identifying the required document. • A note under or beside each field: "jpg, png, docx or pdf files only" • A button or area labeled “Upload File” to upload the supported file. | F35: PASSED
A36: =IF(B36<>"", "US-5-TC-" & TEXT(COUNTA($B$3:B36), "00"), "") -> US-5-TC-34 | B36: Verify that the user is able to select “No” for “Is this a Loan Mortgage?” | C36: 1. User must be on the Sta. Rosa Payroll Portal. 2. User must be on the Login page. 3. User must be logged in the Assessor's Office portal 4. User must be on the request page of Certificate of Application | D36: 1. Search for the Assessor Office login page. 2. Log in using a registered email and password, and check the Terms & Conditions checkbox. 3. Click the Submit button. 4. Check the OTP verification sent to the registered email. 5. Enter the OTP in the verification field. 6. Click the New Request button. 7. Select Certificate of True Copy of Tax Declaration under Type of Certificate. 8. Select Transfer of Tax Declaration under Type of Certificate. 9. Choose the Personal option under Claiming. 10. Upload a valid file (.jpg, .png, .docx, or .pdf) to the following fields: • Contract of Lease • Deed of Absolute Sale (DOAS) • Proof of Ownership • Contract to Sell 11. Select No for “Are you a Company/Bank Developer?” 12. Select No for “Is this a Loan Mortgage?” 12. Fill out all remaining required fields. 13. Click Submit button. | E36: When the user clicks or selects the “No” option for the question “Is this a Loan Mortgage?”: • The system should register the selection without delay or requiring a page reload. • The selection should be visually confirmed (e.g., radio button becomes filled or highlighted). • The “Photocopy of Loan Agreement” section should not appear at all if it hasn't already been shown. | F36: PASSED
A37: =IF(B37<>"", "US-5-TC-" & TEXT(COUNTA($B$3:B37), "00"), "") -> US-5-TC-35 | B37: Verify that selecting “Yes” for “Is this a Loan Mortgage?” allows successful upload of valid file types in the "Photocopy of Loan Agreement" upload field. | C37: 1. User must be on the Sta. Rosa Payroll Portal. 2. User must be on the Login page. 3. User must be logged in the Assessor's Office portal 4. User must be on the request page of Certificate of Application | D37: 1. Search for the Assessor Office login page. 2. Log in using a registered email and password, and check the Terms & Conditions checkbox. 3. Click the Submit button. 4. Check the OTP verification sent to the registered email. 5. Enter the OTP in the verification field. 6. Click the New Request button. 7. Select Certificate of True Copy of Tax Declaration under Type of Certificate. 8. Select Transfer of Tax Declaration under Type of Certificate. 9. Choose the Personal option under Claiming. 10. Upload a valid file (.jpg, .png, .docx, or .pdf) to the following fields: • Contract of Lease • Deed of Absolute Sale (DOAS) • Proof of Ownership • Contract to Sell 11. Select No for “Are you a Company/Bank Developer?” 12. Select No for “Is this a Loan Mortgage?” 12. Fill out all remaining required fields. 13. Click Submit button. | E37: When the user selects “Yes” for the question “Is this a Loan Mortgage?”, the system should: A new section labeled “Photocopy of Loan Agreement” should appear immediately without requiring a page refresh or redirection. Each upload field must contain: • A File label identifying the required document. • A note under or beside each field: "jpg, png, docx or pdf files only" • A button or area labeled “Upload File” to upload the supported file. | F37: PASSED
A38: =IF(B38<>"", "US-5-TC-" & TEXT(COUNTA($B$3:B38), "00"), "") -> US-5-TC-36 | B38: Verify that clicking the 'X' button in the "Photocopy of Loan Agreement" upload field successfully removes the selected file. | C38: 1. User must be on the Sta. Rosa Payroll Portal. 2. User must be on the Login page. 3. User must be logged in the Assessor's Office portal 4. User must be on the request page of Certificate of Application | D38: 1. Search for the Assessor Office login page. 2. Log in using a registered email and password, and check the Terms & Conditions checkbox. 3. Click the Submit button. 4. Check the OTP verification sent to the registered email. 5. Enter the OTP in the verification field. 6. Click the New Request button. 7. Select Certificate of True Copy of Tax Declaration under Type of Certificate. 8. Select Transfer of Tax Declaration under Type of Certificate. 9. Choose the Personal option under Claiming. 10. Upload a valid file (.jpg, .png, .docx, or .pdf) to the following fields: • Contract of Lease • Deed of Absolute Sale (DOAS) • Proof of Ownership • Contract to Sell 11. Select No for “Are you a Company/Bank Developer?” 12. Select No for “Is this a Loan Mortgage?” 12. Fill out all remaining required fields. 13. Click Submit button. | E38: When the user clicks or selects the “No” option for the question “Is this a Loan Mortgage?”: • The system should register the selection without delay or requiring a page reload. • The selection should be visually confirmed (e.g., radio button becomes filled or highlighted). • The “Photocopy of Loan Agreement” section should not appear at all if it hasn't already been shown. | F38: PASSED
A39: =IF(B39<>"", "US-5-TC-" & TEXT(COUNTA($B$3:B39), "00"), "") -> US-5-TC-37 | B39: Verify that submission is blocked when “Is this a Loan Mortgage?” is Yes but the Photocopy of Loan Agreement is not uploaded. | C39: 1. User must be on the Sta. Rosa Payroll Portal. 2. User must be on the Login page. 3. User must be logged in the Assessor's Office portal 4. User must be on the request page of Certificate of Application | D39: 1. Search for the Assessor Office login page. 2. Log in using a registered email and password, and check the Terms & Conditions checkbox. 3. Click the Submit button. 4. Check the OTP verification sent to the registered email. 5. Enter the OTP in the verification field. 6. Click the New Request button. 7. Select Certificate of True Copy of Tax Declaration under Type of Certificate. 8. Select Transfer of Tax Declaration under Type of Certificate. 9. Choose the Personal option under Claiming. 10. Upload a valid file (.jpg, .png, .docx, or .pdf) to the following fields: • Contract of Lease • Deed of Absolute Sale (DOAS) • Proof of Ownership • Contract to Sell 11. Select No for “Are you a Company/Bank Developer?” 12. Select Yes for “Is this a Loan Mortgage?” 13. Do not upload any file to the Photocopy of Loan Agreement field. 14. Fill out the remaining required fields. 15. Click Submit. | E39: When the user selects "Yes" for the "Is this a Loan Mortgage?" question and does not upload the required files under the "Photocopy of Loan Agreement" section: A new section labeled “Photocopy of Loan Agreement” should immediately appear on the form without requiring a page reload. Each upload field must contain: • A File label identifying the required document. • A note under or beside each field: "jpg, png, docx or pdf files only" • A button or area labeled “Upload File” to upload the supported file. Upon clicking Submit, the system should detect that the Photocopy of Loan Agreement files have not been uploaded. The form submission must be blocked. A clear and specific error message should be displayed near each empty file upload field, such as: “Please upload the Photocopy of Loan Agreement” | F39: PASSED
A40: =IF(B40<>"", "US-5-TC-" & TEXT(COUNTA($B$3:B40), "00"), "") -> US-5-TC-38 | B40: Verify That the User Is Unable to Submit If the Checkbox for “I Agree to the Terms & Conditions of the City of Sta. Rosa” Is Not Selected | C40: 1. User must be on the Sta. Rosa Payroll Portal. 2. User must be on the Login page. 3. User must be logged in the Assessor's Office portal 4. User must be on the request page of Certificate of Application | D40: 1. Search for the Assessor Office login page. 2. Log in using a registered email and password, and check the Terms & Conditions checkbox. 3. Click the Submit button. 4. Check the OTP verification sent to the registered email. 5. Enter the OTP in the verification field. 6. Click the New Request button. 7. Select Certificate of True Copy of Tax Declaration under Type of Certificate. 8. Select Transfer of Tax Declaration under Type of Certificate. 9. Choose the Personal option under Claiming. 10. Upload a valid file (.jpg, .png, .docx, or .pdf) to the following fields: • Contract of Lease • Deed of Absolute Sale (DOAS) • Proof of Ownership • Contract to Sell 11. Select No for “Are you a Company/Bank Developer?” 12. Select Yes for “Is this a Loan Mortgage?” 13. Attempt to upload an invalid file type (e.g., .exe, .txt, .zip) in the Photocopy of Loan Agreement field. 14. Fill out the remaining required fields. 15. Do not check the I agree to the Terms & Conditions of the City of Sta Rosa 16. Click Submit. | E40: The system prevents the form submission. An appropriate validation message is displayed, such as: “You must agree to the Terms & Conditions of the City of Sta. Rosa before submitting.” The Submit button remains disabled or the submission is blocked until the checkbox is selected. | F40: PASSED
A41: =IF(B41<>"", "US-5-TC-" & TEXT(COUNTA($B$3:B41), "00"), "") -> US-5-TC-39 | B41: Verify That the User Can Save the Certificate Application Form as Draft | C41: 1. User must be on the Sta. Rosa Payroll Portal. 2. User must be on the Login page. 3. User must be logged in the Assessor's Office portal 4. User must be on the request page of Certificate of Application | D41: 1. Search for the Assessor Office login page. 2. Log in using a registered email and password, and check the Terms & Conditions checkbox. 3. Click the Submit button. 4. Check the OTP verification sent to the registered email. 5. Enter the OTP in the verification field. 6. Click the New Request button. 7. Select Certificate of True Copy of Tax Declaration under Type of Certificate. 8. Select Transfer of Tax Declaration under Type of Certificate. 9. Choose the Personal option under Claiming. 10. Upload a valid file (.jpg, .png, .docx, or .pdf) to the following fields: • Contract of Lease • Deed of Absolute Sale (DOAS) • Proof of Ownership • Contract to Sell 11. Select No for “Are you a Company/Bank Developer?” 12. Select Yes for “Is this a Loan Mortgage?” 13. Attempt to upload an invalid file type (e.g., .exe, .txt, .zip) in the Photocopy of Loan Agreement field. 14. Fill out the remaining required fields. 15. Click the checkbox the I agree to the Terms & Conditions of the City of Sta Rosa 16. Click Save as Draft. | E41: The system saves the current state of the form without requiring all mandatory fields to be completed. The user can later retrieve and continue editing the saved draft. No validation errors are triggered during draft saving. | F41: FAILED | G41: No confirmation message displayed
A42: =IF(B42<>"", "US-5-TC-" & TEXT(COUNTA($B$3:B42), "00"), "") -> US-5-TC-40 | B42: Verify That the User Can Successfully Submit the Form With All Valid and Required Data | C42: 1. User must be on the Sta. Rosa Payroll Portal. 2. User must be on the Login page. 3. User must be logged in the Assessor's Office portal 4. User must be on the request page of Certificate of Application | D42: 1. Search for the Assessor Office login page. 2. Log in using a registered email and password, and check the Terms & Conditions checkbox. 3. Click the Submit button. 4. Check the OTP verification sent to the registered email. 5. Enter the OTP in the verification field. 6. Click the New Request button. 7. Select Certificate of True Copy of Tax Declaration under Type of Certificate. 8. Select Transfer of Tax Declaration under Type of Certificate. 9. Choose the Personal option under Claiming. 10. Upload a valid file (.jpg, .png, .docx, or .pdf) to the following fields: • Contract of Lease • Deed of Absolute Sale (DOAS) • Proof of Ownership • Contract to Sell 11. Select No for “Are you a Company/Bank Developer?” 12. Select Yes for “Is this a Loan Mortgage?” 13. Attempt to upload an invalid file type (e.g., .exe, .txt, .zip) in the Photocopy of Loan Agreement field. 14. Fill out the remaining required fields. 15. Click the checkbox the I agree to the Terms & Conditions of the City of Sta Rosa 16. Click Submit. | E42: The system validates all inputs and uploads. The form is successfully submitted without errors. The user is redirected or given the option to view the submitted application status. | F42: PASSED
A43: =IF(B43<>"", "US-5-TC-" & TEXT(COUNTA($B$3:B43), "00"), "") -> US-5-TC-41 | B43: Verify That the Form Submission Is Blocked If Any Required Fields or Validations Are Missing or Invalid | C43: 1. User must be on the Sta. Rosa Payroll Portal. 2. User must be on the Login page. 3. User must be logged in the Assessor's Office portal 4. User must be on the request page of Certificate of Application | D43: 1. Search for the Assessor Office login page. 2. Log in using a registered email and password, and check the Terms & Conditions checkbox. 3. Click the Submit button. 4. Check the OTP verification sent to the registered email. 5. Enter the OTP in the verification field. 6. Click the New Request button. 7. Select Certificate of True Copy of Tax Declaration under Type of Certificate. 8. Select Transfer of Tax Declaration under Type of Certificate. 9. Choose the Personal option under Claiming. 10. Upload a valid file (.jpg, .png, .docx, or .pdf) to the following fields: • Contract of Lease • Deed of Absolute Sale (DOAS) • Proof of Ownership • Contract to Sell 11. Select No for “Are you a Company/Bank Developer?” 12. Select Yes for “Is this a Loan Mortgage?” 13. Attempt to upload an invalid file type (e.g., .exe, .txt, .zip) in the Photocopy of Loan Agreement field. 14. Fill out the remaining required fields. 15. Click the checkbox the I agree to the Terms & Conditions of the City of Sta Rosa 16. Click Submit. | E43: The system prevents form submission. Appropriate validation error messages appear next to each missing or invalid field (e.g., “This field is required,” “Please upload a valid file in .jpg, .png, .docx, or .pdf format”). The user remains on the form page until all errors are corrected. The Submit button remains disabled or the submission does not proceed until all validations pass. | F43: CLARIFICATION | G43: when submitting application and triggering an error validation, page shoots back up to the top. hopefully can adjust to staying in current view/position on the page instead of having to scroll all the way down again
A44: =IF(B44<>"", "US-5-TC-" & TEXT(COUNTA($B$3:B44), "00"), "") -> US-5-TC-42 | B44: Verify that the user receives an SMS when the request for Certificate of True Copy of Tax Declaration is saved as Draft | C44: 1. User must be on the Sta. Rosa Payroll Portal. 2. User must be on the Login page. 3. User must be logged in the Assessor's Office portal 4. User must be on the request page of Certificate of Application | D44: 1. Fill out the needed requirement on the Certificate of Application form 2. Click Save a Draft button 3. Navigate the SMS alert from STA ROSA | E44: The system shall send an SMS notification to the registered mobile number with the following message: • Santa Rosa Assessor’s Office: Your certificate request <$request_id> has been received and saved as Draft. You will be notified of further updates. The system shall send an email notification to the registered email address with the following details: Subject: Acknowledgement of Your Certificate Request – <$request_id> Hi <$name>, Good day! This is to acknowledge that we have successfully received your certificate request. It is now in the queue and will be routed to the City Assessor's Office for evaluation. REQUEST DETAILS Request ID: <$request_id> Transaction Date: <$transaction_date> Certificates Requested: <$certificates_requested> You will receive SMS and email notifications for any updates related to your request. Thank you and have a great day! Sincerely yours, Santa Rosa Assessor's Office Administrator | F44: OPEN
A45: =IF(B45<>"", "US-5-TC-" & TEXT(COUNTA($B$3:B45), "00"), "") -> US-5-TC-43 | B45: Verify that the user receives an Email when the request for Certificate of True Copy of Tax Declaration is saved as Draft | C45: 1. User must be on the Sta. Rosa Payroll Portal. 2. User must be on the Login page. 3. User must be logged in the Assessor's Office portal 4. User must be on the request page of Certificate of Application | D45: 1. Fill out the needed requirement on the Certificate of Application form 2. Click Save a Draft button 3. Navigate the email alert from STA ROSA | E45: The system shall send an email with the following message: • Santa Rosa Assessor’s Office: Your certificate request <$request_id> has been received and saved as Draft. You will be notified of further updates. The system shall send an email notification to the registered email address with the following details: Subject: Acknowledgement of Your Certificate Request – <$request_id> Hi <$name>, Good day! This is to acknowledge that we have successfully received your certificate request. It is now in the queue and will be routed to the City Assessor's Office for evaluation. REQUEST DETAILS Request ID: <$request_id> Transaction Date: <$transaction_date> Certificates Requested: <$certificates_requested> You will receive SMS and email notifications for any updates related to your request. Thank you and have a great day! Sincerely yours, Santa Rosa Assessor's Office Administrator | F45: OPEN
A46: =IF(B46<>"", "US-5-TC-" & TEXT(COUNTA($B$3:B46), "00"), "") -> US-5-TC-44 | B46: Verify that the user receives an SMS when status is changed to Pending Review for the Certificate of True Copy of Tax Declaration request | C46: 1. User must be on the Sta. Rosa Payroll Portal. 2. User must be on the Login page. 3. User must be logged in the Assessor's Office portal 4. User must be on the request page of Certificate of Application | D46: 1. Fill out all required fields in the Certificate of Application form. 2. Click the Submit button. 3. Wait for status change notification. | E46: The system shall send an SMS notification to the registered mobile number with the following message: • Santa Rosa Assessor’s Office: Assessor's Office: Certificate Request <$request_id> Received - Pending Review The system shall send an email notification to the registered email address with the following details: Hi <$name>, Good day! This is to acknowledge that we have successfully received your certificate request. It is now in the queue and will be routed to the City Assessor's Office for evaluation. Request ID: <$request_id> Transaction Date: <$transaction_date> Certificates Requested: <$certificates_requested> You will receive SMS and email notifications for any updates related to your request. | F46: OPEN
A47: =IF(B47<>"", "US-5-TC-" & TEXT(COUNTA($B$3:B47), "00"), "") -> US-5-TC-45 | B47: Verify that the user receives an Email when status is changed to Pending Review for the Certificate of True Copy of Tax Declaration request | C47: 1. User must be on the Sta. Rosa Payroll Portal. 2. User must be on the Login page. 3. User must be logged in the Assessor's Office portal 4. User must be on the request page of Certificate of Application | D47: 1. Fill out all required fields in the Certificate of Application form. 2. Click the Submit button. 3. Wait for status change notification. | E47: The system shall send an Email notification to the registered mobile number with the following message: • Santa Rosa Assessor’s Office: Assessor's Office: Certificate Request <$request_id> Received - Pending Review The system shall send an email notification to the registered email address with the following details: Hi <$name>, Good day! This is to acknowledge that we have successfully received your certificate request. It is now in the queue and will be routed to the City Assessor's Office for evaluation. Request ID: <$request_id> Transaction Date: <$transaction_date> Certificates Requested: <$certificates_requested> You will receive SMS and email notifications for any updates related to your request. | F47: OPEN
A48: =IF(B48<>"", "US-5-TC-" & TEXT(COUNTA($B$3:B48), "00"), "") -> US-5-TC-46 | B48: Verify SMS is sent when status is changed to Under Review for the Certificate of True Copy of Tax Declaration | C48: 1. User must be on the Sta. Rosa Payroll Portal. 2. User must be on the Login page. 3. User must be logged in the Assessor's Office portal 4. User must be on the request page of Certificate of Application | D48: 1. Fill out all required fields in the Certificate of Application form. 2. Click the Submit button. 3. Wait for status change notification. | E48: The system shall send an email notification to the registered email address of the applicant. | F48: OPEN
A49: =IF(B49<>"", "US-5-TC-" & TEXT(COUNTA($B$3:B49), "00"), "") -> US-5-TC-47 | B49: Verify Email is sent when status is changed to Under Review for the Certificate of True Copy of Tax Declaration | C49: 1. User must be on the Sta. Rosa Payroll Portal. 2. User must be on the Login page. 3. User must be logged in the Assessor's Office portal 4. User must be on the request page of Certificate of Application | D49: 1. Fill out all required fields in the Certificate of Application form. 2. Click the Submit button. 3. Wait for status change notification. | E49: The system shall send an email notification to the registered email address of the applicant. | F49: OPEN
A50: =IF(B50<>"", "US-5-TC-" & TEXT(COUNTA($B$3:B50), "00"), "") -> US-5-TC-48 | B50: Verify SMS is sent when status is Requires Changes for the Certificate of True Copy of Tax Declaration request | C50: 1. User must be on the Sta. Rosa Payroll Portal. 2. User must be on the Login page. 3. User must be logged in the Assessor's Office portal 4. User must be on the request page of Certificate of Application | D50: 1. Fill out all required fields in the Certificate of Application form. 2. Click the Submit button. 3. Wait for status change notification. | E50: The system shall send an email notification to the registered email address of the applicant. | F50: OPEN
A51: =IF(B51<>"", "US-5-TC-" & TEXT(COUNTA($B$3:B51), "00"), "") -> US-5-TC-49 | B51: Verify Email is sent when status is Requires Changes for the Certificate of True Copy of Tax Declaration request | C51: 1. User must be on the Sta. Rosa Payroll Portal. 2. User must be on the Login page. 3. User must be logged in the Assessor's Office portal 4. User must be on the request page of Certificate of Application | D51: 1. Fill out all required fields in the Certificate of Application form. 2. Click the Submit button. 3. Wait for status change notification. | E51: The system shall send an email notification to the registered email address of the applicant. | F51: OPEN
A52: =IF(B52<>"", "US-5-TC-" & TEXT(COUNTA($B$3:B52), "00"), "") -> US-5-TC-50 | B52: Verify SMS is sent when status is Awaiting Payment for the Certificate of True Copy of Tax Declaration | C52: 1. User must be on the Sta. Rosa Payroll Portal. 2. User must be on the Login page. 3. User must be logged in the Assessor's Office portal 4. User must be on the request page of Certificate of Application | D52: 1. Fill out all required fields in the Certificate of Application form. 2. Click the Submit button. 3. Wait for status change notification. | E52: The system shall send an email notification to the registered email address of the applicant. | F52: OPEN
A53: =IF(B53<>"", "US-5-TC-" & TEXT(COUNTA($B$3:B53), "00"), "") -> US-5-TC-51 | B53: Verify Email is sent when status is Awaiting Payment for the Certificate of True Copy of Tax Declaration | C53: 1. User must be on the Sta. Rosa Payroll Portal. 2. User must be on the Login page. 3. User must be logged in the Assessor's Office portal 4. User must be on the request page of Certificate of Application | D53: 1. Fill out all required fields in the Certificate of Application form. 2. Click the Submit button. 3. Wait for status change notification. | E53: The system shall send an email notification to the registered email address of the applicant. | F53: OPEN
A54: =IF(B54<>"", "US-5-TC-" & TEXT(COUNTA($B$3:B54), "00"), "") -> US-5-TC-52 | B54: Verify SMS is sent when status is Payment Verification for the Certificate of True Copy of Tax Declaration | C54: 1. User must be on the Sta. Rosa Payroll Portal. 2. User must be on the Login page. 3. User must be logged in the Assessor's Office portal 4. User must be on the request page of Certificate of Application | D54: 1. Fill out all required fields in the Certificate of Application form. 2. Click the Submit button. 3. Wait for status change notification. | E54: The system shall send an email notification to the registered email address of the applicant. | F54: OPEN
A55: =IF(B55<>"", "US-5-TC-" & TEXT(COUNTA($B$3:B55), "00"), "") -> US-5-TC-53 | B55: Verify SMS is sent when status is Payment Verification for the Certificate of True Copy of Tax Declaration | C55: 1. User must be on the Sta. Rosa Payroll Portal. 2. User must be on the Login page. 3. User must be logged in the Assessor's Office portal 4. User must be on the request page of Certificate of Application | D55: 1. Fill out all required fields in the Certificate of Application form. 2. Click the Submit button. 3. Wait for status change notification. | E55: The system shall send an email notification to the registered email address of the applicant. | F55: OPEN
... A62: =IF(B62<>"", "US-5-TC-" & TEXT(COUNTA($B$3:B62), "00"), "") -> US-5-TC-60 | B62: Verify Email is sent when status is Certificate Claimed for the Certificate of True Copy of Tax Declaration | C62: 1. User must be on the Sta. Rosa Payroll Portal. 2. User must be on the Login page. 3. User must be logged in the Assessor's Office portal 4. User must be on the request page of Certificate of Application | D62: 1. Fill out all required fields in the Certificate of Application form. 2. Click the Submit button. 3. Wait for status change notification. | E62: The system shall send an email notification to the registered email address of the applicant. | F62: OPEN

Sheet PG-US-06
A1: PG-US-06 | B1: USER STORY: As a property owner, I want to apply for a Certificate of True Copy of Tax Declaration So that I can process my property documentation And have it claimed by an Authorized Representative on my behalf.
A2: Test Case ID | B2: Test Objective | C2: Preconditions | D2: Test Steps | E2: Expected Results | F2: Status | G2: Comments
A3: =IF(B1<>"", "US-6-TC-" & TEXT(COUNTA($B$3:B3), "00"), "") -> US-6-TC-01 | B3: Verify that the user is able to select both the "Certificate of True Copy of Tax Declaration" checkbox under the Type of Certificate section. | C3: 1. User must be on the Sta. Rosa Payroll Portal. 2. User must be on the Login page. 3. User must be logged in the Assessor's Office portal 4. User must be on the request page of Certificate of Application | D3: 1. Search Assessor office login 2. Login with registered email and password and checkbox of T&C. 3. Click Submit button 4. Check OTP Verification sent on email. 5. Put the OTP on the Verification 6. Click the "New Request" button 7. Click the Certificate of True Copy of Tax Declaration under Type of Certificate 8. Click the transfer of Tax Declaration 9. Chose the Authorized Representative option under Claiming | E3: Type of Certificate: The user successfully selects both of the following checkboxes: a) Certificate of True Copy of Tax Declaration Claiming Method: -- The user selects the Authorized Representative radio button. ID of Property Owner with 3 Signatures: - The required document is successfully uploaded via the drag-and-drop or upload file field. Certification Requirements: Note: All fields are mandatory. The system will not accept the submission if a document is not uploaded. Hover over the information icon to see the list of Valid IDs. The user uploads valid files (in jpg, png, docx, or pdf format) for all of the following: a) Contract of Lease b) Deed of Absolute Sale (DOAS) c) Proof of Ownership d) Contract to Sell Are you a Company/Bank Developer? Yes No option → Yes Secretary’s Certificate and one (1)employee ID jpg, png, docx or pdf files only File Upload file button Company/Bank Developer Section When the user selects “Yes” for “Are you a Company/Bank Developer?”: • The system dynamically displays a new section labeled “Secretary’s Certificate and one (1) employee ID” without page reload. • The user is required to upload both the Secretary’s Certificate and Employee ID. • Only valid formats (.jpg, .png, .docx, or .pdf) are accepted. • Submission is blocked if either document is not uploaded. Loan Mortgage Section When the user selects “Yes” for “Is this a Loan Mortgage?”: • A new upload field labeled “Photocopy of Loan Agreement” is immediately displayed. • Only files in .jpg, .png, .docx, or .pdf format are accepted. • Submission is blocked if the field is left empty. Authorized Representative Requirements The system displays the following required fields when the Authorized Representative option is selected: • ID of Representative with 3 Signatures • Special Power of Attorney (SPA) • Authorization Letter - Valid formats: .jpg, .png, .docx, or .pdf. - The system must confirm all files are uploaded and valid before allowing submission. Terms and Conditions Agreement • The checkbox labeled “I agree to the Terms & Conditions of the City of Sta Rosa” must be selected. - If unchecked, the Submit button remains disabled or submission is blocked with a prompt to accept the terms. Save Draft and Submit button If all required fields are completed, valid documents are uploaded, and the terms are agreed to: • The user can click Save as Draft to save the form without submitting. • The user can click Submit to finalize and submit the application. | F3: PASSED
A4: =IF(B1<>"", "US-6-TC-" & TEXT(COUNTA($B$3:B4), "00"), "") -> US-6-TC-02 | B4: Verify that the user is able to select the “Authorized Representative” radio button under the Claiming section. | C4: 1. User must be on the Sta. Rosa Payroll Portal. 2. User must be on the Login page. 3. User must be logged in the Assessor's Office portal 4. User must be on the request page of Certificate of Application | D4: 1. Search Assessor office login 2. Login with registered email and password and checkbox of T&C. 3. Click Submit button 4. Check OTP Verification sent on email. 5. Put the OTP on the Verification 6. Click the "New Request" button 7. Click the Certificate of True Copy of Tax Declaration under Type of Certificate 8. Click the transfer of Tax Declaration 9. Chose the Authorized Representative option under Claiming | E4: Type of Certificate: The user successfully selects both of the following checkboxes: a) Certificate of True Copy of Tax Declaration Claiming Method: -- The user selects the Authorized Representative radio button. ID of Property Owner with 3 Signatures: - The required document is successfully uploaded via the drag-and-drop or upload file field. Certification Requirements: Note: All fields are mandatory. The system will not accept the submission if a document is not uploaded. Hover over the information icon to see the list of Valid IDs. The user uploads valid files (in jpg, png, docx, or pdf format) for all of the following: a) Contract of Lease b) Deed of Absolute Sale (DOAS) c) Proof of Ownership d) Contract to Sell Are you a Company/Bank Developer? Yes No option → Yes Secretary’s Certificate and one (1)employee ID jpg, png, docx or pdf files only File Upload file button Company/Bank Developer Section When the user selects “Yes” for “Are you a Company/Bank Developer?”: • The system dynamically displays a new section labeled “Secretary’s Certificate and one (1) employee ID” without page reload. • The user is required to upload both the Secretary’s Certificate and Employee ID. • Only valid formats (.jpg, .png, .docx, or .pdf) are accepted. • Submission is blocked if either document is not uploaded. Loan Mortgage Section When the user selects “Yes” for “Is this a Loan Mortgage?”: • A new upload field labeled “Photocopy of Loan Agreement” is immediately displayed. • Only files in .jpg, .png, .docx, or .pdf format are accepted. • Submission is blocked if the field is left empty. Authorized Representative Requirements The system displays the following required fields when the Authorized Representative option is selected: • ID of Representative with 3 Signatures • Special Power of Attorney (SPA) • Authorization Letter - Valid formats: .jpg, .png, .docx, or .pdf. - The system must confirm all files are uploaded and valid before allowing submission. Terms and Conditions Agreement • The checkbox labeled “I agree to the Terms & Conditions of the City of Sta Rosa” must be selected. - If unchecked, the Submit button remains disabled or submission is blocked with a prompt to accept the terms. Save Draft and Submit button If all required fields are completed, valid documents are uploaded, and the terms are agreed to: • The user can click Save as Draft to save the form without submitting. • The user can click Submit to finalize and submit the application. | F4: PASSED
A5: =IF(B3<>"", "US-6-TC-" & TEXT(COUNTA($B3:B$5), "00"), "") -> US-6-TC-03 | B5: Verify that Authorized Representative Requirements appear when "Authorized Representative" is selected on the Claiming | C5: 1. User must be on the Sta. Rosa Payroll Portal. 2. User must be on the Login page. 3. User must be logged in the Assessor's Office portal 4. User must be on the request page of Certificate of Application | D5: 1. Search Assessor office login 2. Login with registered email and password and checkbox of T&C. 3. Click Submit button 4. Check OTP Verification sent on email. 5. Put the OTP on the Verification 6. Click the "New Request" button 7. Click the Certificate of True Copy of Tax Declaration under Type of Certificate 8. Click the transfer of Tax Declaration 9. Chose the Authorized Representative option under Claiming | E5: Type of Certificate: The user successfully selects both of the following checkboxes: a) Certificate of True Copy of Tax Declaration Claiming Method: -- The user selects the Authorized Representative radio button. ID of Property Owner with 3 Signatures: - The required document is successfully uploaded via the drag-and-drop or upload file field. Certification Requirements: Note: All fields are mandatory. The system will not accept the submission if a document is not uploaded. Hover over the information icon to see the list of Valid IDs. The user uploads valid files (in jpg, png, docx, or pdf format) for all of the following: a) Contract of Lease b) Deed of Absolute Sale (DOAS) c) Proof of Ownership d) Contract to Sell Are you a Company/Bank Developer? Yes No option → Yes Secretary’s Certificate and one (1)employee ID jpg, png, docx or pdf files only File Upload file button Company/Bank Developer Section When the user selects “Yes” for “Are you a Company/Bank Developer?”: • The system dynamically displays a new section labeled “Secretary’s Certificate and one (1) employee ID” without page reload. • The user is required to upload both the Secretary’s Certificate and Employee ID. • Only valid formats (.jpg, .png, .docx, or .pdf) are accepted. • Submission is blocked if either document is not uploaded. Loan Mortgage Section When the user selects “Yes” for “Is this a Loan Mortgage?”: • A new upload field labeled “Photocopy of Loan Agreement” is immediately displayed. • Only files in .jpg, .png, .docx, or .pdf format are accepted. • Submission is blocked if the field is left empty. Authorized Representative Requirements The system displays the following required fields when the Authorized Representative option is selected: • ID of Representative with 3 Signatures • Special Power of Attorney (SPA) • Authorization Letter - Valid formats: .jpg, .png, .docx, or .pdf. - The system must confirm all files are uploaded and valid before allowing submission. Terms and Conditions Agreement • The checkbox labeled “I agree to the Terms & Conditions of the City of Sta Rosa” must be selected. - If unchecked, the Submit button remains disabled or submission is blocked with a prompt to accept the terms. Save Draft and Submit button If all required fields are completed, valid documents are uploaded, and the terms are agreed to: • The user can click Save as Draft to save the form without submitting. • The user can click Submit to finalize and submit the application. | F5: PASSED
A6: =IF(B4<>"", "US-6-TC-" & TEXT(COUNTA($B3:B$6), "00"), "") -> US-6-TC-04 | B6: Verify that the ID of Property Owner with three (3) Signatures can be successfully uploaded in valid formats (e.g. jpg, png, docx, pdf) when applying for Certificate of True Copy of Tax Declaration or Transfer of Tax Declaration with “Authorize Representative” claiming method | C6: 1. User must be on the Sta. Rosa Payroll Portal. 2. User must be on the Login page. 3. User must be logged in the Assessor's Office portal 4. User must be on the request page of Certificate of Application | D6: 1. Search for the Assessor Office login page. 2. Log in using a registered email and password, and check the Terms & Conditions checkbox. 3. Click the Submit button. 4. Check the OTP verification sent to the registered email. 5. Enter the OTP in the verification field. 6. Click the New Request button. 7. Select Certificate of True Copy of Tax Declaration under Type of Certificate. 8. Select Transfer of Tax Declaration under Type of Certificate. 9. Choose the Personal option under Claiming. 10. Click the information icon beside the note in the Certificate Requirements section. | E6: The user shall be able to view the name of the file that has been uploaded, displayed below the "ID of Property Owner with three (3) Signatures" upload field. | F6: PASSED
A7: =IF(B5<>"", "US-6-TC-" & TEXT(COUNTA($B3:B$7), "00"), "") -> US-6-TC-05 | B7: Verify that the uploaded "ID of Property Owner with three (3) Signatures" file can be removed by clicking the “X” button located beside the uploaded file . | C7: 1. User must be on the Sta. Rosa Payroll Portal. 2. User must be on the Login page. 3. User must be logged in the Assessor's Office portal 4. User must be on the request page of Certificate of Application | D7: 1. Search for Assessor Office login page. 2. Login using registered email and password, and check the Terms & Conditions checkbox. 3. Click the Submit button. 4. Check for OTP verification sent via email. 5. Enter the OTP on the Verification page. 6. Click the New Request button. 7. Select Certificate of True Copy of Tax Declaration under Type of Certificate. 8. Select Transfer of Tax Declaration under Type of Certificate. 9. Choose the Personal option under Claiming. 10. Upload a valid file for "ID of Property Owner with three (3) Signatures." 11. Click the “X” button beside the uploaded file to remove it. | E7: The uploaded "ID of Property Owner with three (3) Signatures" file shall be successfully removed from the form when the user clicks the “X” button located beside the uploaded file, and the upload field shall be cleared to allow a new file to be uploaded. | F7: PASSED
A8: =IF(B6<>"", "US-6-TC-" & TEXT(COUNTA($B3:B$8), "00"), "") -> US-6-TC-06 | B8: Verify that only one file can be uploaded for the "ID of Property Owner with three (3) Signatures" field and that the system processes only the uploaded file when applying | C8: 1. User must be on the Sta. Rosa Payroll Portal. 2. User must be on the Login page. 3. User must be logged in the Assessor's Office portal 4. User must be on the request page of Certificate of Application | D8: 1. Search for Assessor Office login page. 2. Login using registered email and password, and check the Terms & Conditions checkbox. 3. Click the Submit button. 4. Check for OTP verification sent via email. 5. Enter the OTP on the Verification page. 6. Click the New Request button. 7. Select Certificate of True Copy of Tax Declaration under Type of Certificate. 8. Select Transfer of Tax Declaration under Type of Certificate. 9. Choose the Personal option under Claiming. 10. Upload a valid file for "ID of Property Owner with three (3) Signatures." 11. Attempt to upload a second file for the same field. | E8: The system shall allow uploading only one file for the "ID of Property Owner with three (3) Signatures" field. If a new file is uploaded, it shall replace the previously uploaded file. The system shall process only the currently uploaded file during the application submission. | F8: PASSED
A9: =IF(B6<>"", "US-6-TC-" & TEXT(COUNTA($B3:B$9), "00"), "") -> US-6-TC-07 | B9: Verify that uploading a new file for the "ID of Property Owner with three (3) Signatures" field replaces the previously uploaded file | C9: 1. User must be on the Sta. Rosa Payroll Portal. 2. User must be on the Login page. 3. User must be logged in the Assessor's Office portal 4. User must be on the request page of Certificate of Application | D9: 1. Search for Assessor Office login page. 2. Login using registered email and password, and check the Terms & Conditions checkbox. 3. Click the Submit button. 4. Check for OTP verification sent via email. 5. Enter the OTP on the Verification page. 6. Click the New Request button. 7. Select Certificate of True Copy of Tax Declaration under Type of Certificate. 8. Select Transfer of Tax Declaration under Type of Certificate. 9. Choose the Personal option under Claiming. 10. Upload a valid file for "ID of Property Owner with three (3) Signatures." 11. Upload a new file for the same field and observe the system’s behavior. | E9: When a new file is uploaded for the "ID of Property Owner with three (3) Signatures" field, the system shall replace the previously uploaded file with the new one, displaying only the latest uploaded file in the upload section. | F9: PASSED
A10: =IF(B6<>"", "US-6-TC-" & TEXT(COUNTA($B3:B$10), "00"), "") -> US-6-TC-08 | B10: Verify that clicking the information icon displays the Certificate Requirements pop-up message. | C10: 1. User must be on the Sta. Rosa Payroll Portal. 2. User must be on the Login page. 3. User must be logged in the Assessor's Office portal 4. User must be on the request page of Certificate of Application 5. Scroll down to the see the Certificate Requirements 6. User must click the information icon | D10: 1. Search for the Assessor Office login page. 2. Log in using a registered email and password, and check the Terms & Conditions checkbox. 3. Click the Submit button. 4. Check the OTP verification sent to the registered email. 5. Enter the OTP in the verification field. 6. Click the New Request button. 7. Select Certificate of True Copy of Tax Declaration under Type of Certificate. 8. Select Transfer of Tax Declaration under Type of Certificate. 9. Choose the Personal option under Claiming. 10. Click the information icon beside the note in the Certificate Requirements section. | E10: Upon accessing the Certificate Requirements section, the system shall display a pop-up containing the following information: Certificate Requirements • Applicable for the following certificate types: • Certificate of True Copy of Tax Declaration • Certificate of Aggregate Landholdings • Certification of No-Property • Other Certifications Required Documents: • ID of the Property Owner with three (3) signatures • Original Copy of the Contract of Lease • Original Copy of the Deed of Absolute Sale (DOAS) • Original Copy of the Contract to Sell • Proof of Ownership • If Company / Bank Developer: Secretary’s Certificate and one (1) employee ID • If Loan Mortgage: Photocopy of Loan Agreement Transfer of Tax Declaration Required Documents: • ID of the Property Owner with three (3) signatures • Certified True Copy of Title • Xerox Copy of Deed of Sale / Donation / Extra Judicial Settlement • Xerox Copy of Real Property Tax Receipt or Tax Clearance • Xerox of Transfer Tax Receipt or Certification of Transfer Tax • Xerox Copy of C.A.R. (B.I.R.) • Receipt from the Register of Deeds for the New Title • For subdivided lots: Copy of Subdivision Plan • For canceled titles: Certified Canceled Title • For foreclosed lots: Certification of Sale and Affidavit of Consolidation of Ownership Additional Documents for Authorized Representative Required Documents: • ID of the Authorized Representative with three (3) signatures • Original Copy of the Authorization Letter • Original Copy of the Special Power of Attorney (SPA) A Close button shall be present to allow users to dismiss the pop-up message. | F10: PASSED
A11: =IF(B6<>"", "US-6-TC-" & TEXT(COUNTA($B3:B$11), "00"), "") -> US-6-TC-09 | B11: Verify that the form prevents submission when the required ID of Property Owner with three (3) Signatures is not uploaded for Certificate of True Copy or Transfer of Tax Declaration | C11: 1. User must be on the Sta. Rosa Payroll Portal. 2. User must be on the Login page. 3. User must be logged in the Assessor's Office portal 4. User must be on the request page of Certificate of Application | D11: 1. Search for the Assessor Office login page. 2. Log in using a registered email and password, and check the Terms & Conditions checkbox. 3. Click the Submit button. 4. Check the OTP verification sent to the registered email. 5. Enter the OTP in the verification field. 6. Click the New Request button. 7. Select Certificate of True Copy of Tax Declaration under Type of Certificate. 8. Select Transfer of Tax Declaration under Type of Certificate. 9. Choose the Personal option under Claiming. 10. Do not upload any file in the ID of Property Owner with three (3) Signatures upload field. 11. Click the Submit button | E11: The form does not allow submission unless the required file for the ID of Property Owner with three (3) Signatures is uploaded. A clear validation message or notification is displayed near the upload field or as a general alert, stating: 1.) “The ID of Property Owner with three (3) Signatures is required. Please upload jpg, png, docx or pdf files only.” 2.) The user remains on the same form page with all previously entered data preserved, except for the missing required file. 3.) The system blocks submission until a valid file in the accepted formats (.jpg, .png, .docx, .pdf) is uploaded for this required field. | F11: PASSED
A12: =IF(B6<>"", "US-6-TC-" & TEXT(COUNTA($B$3:B12), "00"), "") -> US-6-TC-10 | B12: Verify that the system displays an error when uploading an unsupported file type (e.g., .exe, .zip) for the ID of Property Owner with three (3) Signatures | C12: 1. User must be on the Sta. Rosa Payroll Portal. 2. User must be on the Login page. 3. User must be logged in the Assessor's Office portal 4. User must be on the request page of Certificate of Application | D12: 1. Search for the Assessor Office login page. 2. Log in using a registered email and password, and check the Terms & Conditions checkbox. 3. Click the Submit button. 4. Check the OTP verification sent to the registered email. 5. Enter the OTP in the verification field. 6. Click the New Request button. 7. Select Certificate of True Copy of Tax Declaration under Type of Certificate. 8. Select Transfer of Tax Declaration under Type of Certificate. 9. Choose the Personal option under Claiming. 10. Click the information icon beside the note in the Certificate Requirements section. 11. Attempt to upload an unsupported file type (e.g., .exe or .zip) in the ID of Property Owner with three (3) Signatures upload field. | E12: The system shall immediately reject any upload attempt of unsupported file types for the “ID of Property Owner with three (3) Signatures” field (e.g., .exe, .zip). A clear and specific error message is displayed near the upload field or as a pop-up alert, stating: 1.) “The ID of Property Owner with three (3) Signatures is required. Please upload jpg, png, docx or pdf files only.” 2.) The unsupported file is not accepted, saved, or queued for submission in the form. 3.) The user remains on the current application page with all previously entered form data preserved and unaffected. 4.) The upload field is cleared of the invalid file, and the system waits for a valid file format to be uploaded. 5.) Submission is blocked until the user uploads a supported and valid file format. | F12: PASSED
A13: =IF(B7<>"", "US-6-TC-" & TEXT(COUNTA($B$3:B13), "00"), "") -> US-6-TC-11 | B13: Verify that the form prevents submission when the uploaded file for ID of Property Owner with three (3) Signatures is blank, corrupted, or unreadable | C13: 1. User must be on the Sta. Rosa Payroll Portal. 2. User must be on the Login page. 3. User must be logged in the Assessor's Office portal 4. User must be on the request page of Certificate of Application | D13: 1. Search for the Assessor Office login page. 2. Log in using a registered email and password, and check the Terms & Conditions checkbox. 3. Click the Submit button. 4. Check the OTP verification sent to the registered email. 5. Enter the OTP in the verification field. 6. Click the New Request button. 7. Select Certificate of True Copy of Tax Declaration under Type of Certificate. 8. Select Transfer of Tax Declaration under Type of Certificate. 9. Choose the Personal option under Claiming. 10. Attempt to upload a blank, corrupted, or unreadable file in the ID of Property Owner with three (3) Signatures upload field. 11. Click Submit. | E13: The form shall prevent submission if the uploaded file for the “ID of Property Owner with three (3) Signatures” is blank, corrupted, or unreadable. A clear validation message or notification shall be displayed near the upload field or as a general alert, stating: 1.) “The ID of Property Owner with three (3) Signatures is required. Please upload a jpg, png, docx or pdf files only.” 2.) The user shall remain on the current form page with all previously entered data preserved, except for the missing or invalid file. 3.) The system shall block form submission until a valid and readable file in the accepted formats (.jpg, .png, .docx, .pdf) is successfully uploaded for this required field. | F13: PASSED
A14: =IF(B8<>"", "US-6-TC-" & TEXT(COUNTA($B$3:B14), "00"), "") -> US-6-TC-12 | B14: Verify that the system accepts and successfully uploads a valid file (.jpg, .png, .docx, or .pdf) for the Contract of Lease field. | C14: 1. User must be on the Sta. Rosa Payroll Portal. 2. User must be on the Login page. 3. User must be logged in the Assessor's Office portal 4. User must be on the request page of Certificate of Application | D14: 1. Search for the Assessor Office login page. 2. Log in using a registered email and password, and check the Terms & Conditions checkbox. 3. Click the Submit button. 4. Check the OTP verification sent to the registered email. 5. Enter the OTP in the verification field. 6. Click the New Request button. 7. Select Certificate of True Copy of Tax Declaration under Type of Certificate. 8. Select Transfer of Tax Declaration under Type of Certificate. 9. Choose the Personal option under Claiming. 10. In the Contract of Lease upload field, click Upload File, then select a valid .jpg, .png, .docx, or .pdf file. 11. Click Submit. | E14: These are the following details for the certification requirements. All fields are mandatory, and the system will not accept submission without uploading the required documents. Valid file types include .jpg, .png, .docx, or .pdf: Certification Requirements Note: All fields are mandatory. The system will not accept the submission if a document is not uploaded. Hover over the information icon to see the list of Valid IDs. (information icon) a) Contract of Lease jpg, png, docx or pdf files only File Upload File button b) Deed of Absolute Sale (DOAS) jpg, png, docx or pdf files only File Upload File button c) Proof of Ownership jpg, png, docx or pdf files only File Upload File button d) Contract to Sell jpg, png, docx or pdf files only File Upload File button Contract of Lease Field: • Accepts only valid file types: .jpg, .png, .docx, .pdf. | F14: PASSED
A15: =IF(B9<>"", "US-6-TC-" & TEXT(COUNTA($B$3:B15), "00"), "") -> US-6-TC-13 | B15: Verify that the system prevents form submission and displays a validation error when the Contract of Lease upload field is left blank. | C15: 1. User must be on the Sta. Rosa Payroll Portal. 2. User must be on the Login page. 3. User must be logged in the Assessor's Office portal 4. User must be on the request page of Certificate of Application | D15: 1. Search for the Assessor Office login page. 2. Log in using a registered email and password, and check the Terms & Conditions checkbox. 3. Click the Submit button. 4. Check the OTP verification sent to the registered email. 5. Enter the OTP in the verification field. 6. Click the New Request button. 7. Select Certificate of True Copy of Tax Declaration under Type of Certificate. 8. Select Transfer of Tax Declaration under Type of Certificate. 9. Choose the Personal option under Claiming. 10. Leave the “Contract of Lease” field empty. 11. Fill out other required document fields with valid files. 12. Click the "Submit" button. | E15: These are the following details for the certification requirements. All fields are mandatory, and the system will not accept submission without uploading the required documents. Valid file types include .jpg, .png, .docx, or .pdf: Certification Requirements Note: All fields are mandatory. The system will not accept the submission if a document is not uploaded. Hover over the information icon to see the list of Valid IDs. (information icon) a) Contract of Lease jpg, png, docx or pdf files only File Upload File button b) Deed of Absolute Sale (DOAS) jpg, png, docx or pdf files only File Upload File button c) Proof of Ownership jpg, png, docx or pdf files only File Upload File button d) Contract to Sell jpg, png, docx or pdf files only File Upload File button Contract of Lease Field: • Leaving this field blank prevents form submission and shows a required field validation error "Please upload a Contract of Lease document in .jpg, .png, .docx, or .pdf format only." and blocks submission. | F15: PASSED
A16: =IF(B10<>"", "US-6-TC-" & TEXT(COUNTA($B$3:B16), "00"), "") -> US-6-TC-14 | B16: Verify that the system rejects and displays an error message when an unsupported file type (e.g., .exe, .zip) is uploaded to the Contract of Lease field. | C16: 1. User must be on the Sta. Rosa Payroll Portal. 2. User must be on the Login page. 3. User must be logged in the Assessor's Office portal 4. User must be on the request page of Certificate of Application | D16: 1. Search for the Assessor Office login page. 2. Log in using a registered email and password, and check the Terms & Conditions checkbox. 3. Click the Submit button. 4. Check the OTP verification sent to the registered email. 5. Enter the OTP in the verification field. 6. Click the New Request button. 7. Select Certificate of True Copy of Tax Declaration under Type of Certificate. 8. Select Transfer of Tax Declaration under Type of Certificate. 9. Choose the Personal option under Claiming. 10. Attempt to upload an unsupported file format (e.g., .exe or .zip) to the “Contract of Lease” field. 11. Fill other required fields with valid files. 12. Click "Submit." | E16: These are the following details for the certification requirements. All fields are mandatory, and the system will not accept submission without uploading the required documents. Valid file types include .jpg, .png, .docx, or .pdf: Certification Requirements Note: All fields are mandatory. The system will not accept the submission if a document is not uploaded. Hover over the information icon to see the list of Valid IDs. (information icon) a) Contract of Lease jpg, png, docx or pdf files only File Upload File button b) Deed of Absolute Sale (DOAS) jpg, png, docx or pdf files only File Upload File button c) Proof of Ownership jpg, png, docx or pdf files only File Upload File button d) Contract to Sell jpg, png, docx or pdf files only File Upload File button Contract of Lease Field: • Uploading an invalid file type (e.g., .exe, .zip) triggers a clear validation error message "Please upload a Contract of Lease document in .jpg, .png, .docx, or .pdf format only." and blocks submission. | F16: PASSED
A17: =IF(B11<>"", "US-6-TC-" & TEXT(COUNTA($B$3:B17), "00"), "") -> US-6-TC-15 | B17: Verify that the system accepts and successfully uploads a valid file (.jpg, .png, .docx, or .pdf) for the Deed of Absolute Sale (DOAS) field. | C17: 1. User must be on the Sta. Rosa Payroll Portal. 2. User must be on the Login page. 3. User must be logged in the Assessor's Office portal 4. User must be on the request page of Certificate of Application | D17: 1. Search for the Assessor Office login page. 2. Log in using a registered email and password, and check the Terms & Conditions checkbox. 3. Click the Submit button. 4. Check the OTP verification sent to the registered email. 5. Enter the OTP in the verification field. 6. Click the New Request button. 7. Select Certificate of True Copy of Tax Declaration under Type of Certificate. 8. Select Transfer of Tax Declaration under Type of Certificate. 9. Choose the Personal option under Claiming. 10. Upload a valid file format (e.g., .pdf) to the “Deed of Absolute Sale (DOAS)” field. 11. Fill other required fields with valid files. 12. Click "Submit." | E17: These are the following details for the certification requirements. All fields are mandatory, and the system will not accept submission without uploading the required documents. Valid file types include .jpg, .png, .docx, or .pdf: Certification Requirements Note: All fields are mandatory. The system will not accept the submission if a document is not uploaded. Hover over the information icon to see the list of Valid IDs. (information icon) a) Contract of Lease jpg, png, docx or pdf files only File Upload File button b) Deed of Absolute Sale (DOAS) jpg, png, docx or pdf files only File Upload File button c) Proof of Ownership jpg, png, docx or pdf files only File Upload File button d) Contract to Sell jpg, png, docx or pdf files only File Upload File button Deed of Absolute Sale (DOAS) field. • Accepts only valid file types: .jpg, .png, .docx, .pdf. | F17: PASSED
A18: =IF(B12<>"", "US-6-TC-" & TEXT(COUNTA($B$3:B18), "00"), "") -> US-6-TC-16 | B18: Verify that the system prevents form submission and displays a validation error when the Deed of Absolute Sale (DOAS) upload field is left blank. | C18: 1. User must be on the Sta. Rosa Payroll Portal. 2. User must be on the Login page. 3. User must be logged in the Assessor's Office portal 4. User must be on the request page of Certificate of Application | D18: 1. Search for the Assessor Office login page. 2. Log in using a registered email and password, and check the Terms & Conditions checkbox. 3. Click the Submit button. 4. Check the OTP verification sent to the registered email. 5. Enter the OTP in the verification field. 6. Click the New Request button. 7. Select Certificate of True Copy of Tax Declaration under Type of Certificate. 8. Select Transfer of Tax Declaration under Type of Certificate. 9. Choose the Personal option under Claiming. 10. Leave the “DOAS” field empty. 11. Fill other required fields with valid files. 12. Click "Submit." | E18: These are the following details for the certification requirements. All fields are mandatory, and the system will not accept submission without uploading the required documents. Valid file types include .jpg, .png, .docx, or .pdf: Certification Requirements Note: All fields are mandatory. The system will not accept the submission if a document is not uploaded. Hover over the information icon to see the list of Valid IDs. (information icon) a) Contract of Lease jpg, png, docx or pdf files only File Upload File button b) Deed of Absolute Sale (DOAS) jpg, png, docx or pdf files only File Upload File button c) Proof of Ownership jpg, png, docx or pdf files only File Upload File button d) Contract to Sell jpg, png, docx or pdf files only File Upload File button Deed of Absolute Sale (DOAS) field. • Blank uploads trigger a required field validation error, blocking submission "Please upload a Contract of Lease document in .jpg, .png, .docx, or .pdf format only." and blocks submission. | F18: PASSED
A19: =IF(B13<>"", "US-6-TC-" & TEXT(COUNTA($B$3:B19), "00"), "") -> US-6-TC-17 | B19: Verify that the system rejects and displays an error message when an unsupported file type is uploaded to the Deed of Absolute Sale (DOAS) field. | C19: 1. User must be on the Sta. Rosa Payroll Portal. 2. User must be on the Login page. 3. User must be logged in the Assessor's Office portal 4. User must be on the request page of Certificate of Application | D19: 1. Search for the Assessor Office login page. 2. Log in using a registered email and password, and check the Terms & Conditions checkbox. 3. Click the Submit button. 4. Check the OTP verification sent to the registered email. 5. Enter the OTP in the verification field. 6. Click the New Request button. 7. Select Certificate of True Copy of Tax Declaration under Type of Certificate. 8. Select Transfer of Tax Declaration under Type of Certificate. 9. Choose the Personal option under Claiming. 10. Attempt to upload an unsupported file format (e.g., .exe, .zip) in the DOAS field. 11. Fill other required fields with valid files. 12. Click "Submit." | E19: These are the following details for the certification requirements. All fields are mandatory, and the system will not accept submission without uploading the required documents. Valid file types include .jpg, .png, .docx, or .pdf: Certification Requirements Note: All fields are mandatory. The system will not accept the submission if a document is not uploaded. Hover over the information icon to see the list of Valid IDs. (information icon) a) Contract of Lease jpg, png, docx or pdf files only File Upload File button b) Deed of Absolute Sale (DOAS) jpg, png, docx or pdf files only File Upload File button c) Proof of Ownership jpg, png, docx or pdf files only File Upload File button d) Contract to Sell jpg, png, docx or pdf files only File Upload File button Deed of Absolute Sale (DOAS) field. • Uploading an invalid file type (e.g., .exe, .zip) triggers a clear validation error message "Please upload a Contract of Lease document in .jpg, .png, .docx, or .pdf format only." and blocks submission. | F19: PASSED
A20: =IF(B14<>"", "US-6-TC-" & TEXT(COUNTA($B$3:B20), "00"), "") -> US-6-TC-18 | B20: Verify that the system accepts and successfully uploads a valid file (.jpg, .png, .docx, or .pdf) for the Proof of Ownership field. | C20: 1. User must be on the Sta. Rosa Payroll Portal. 2. User must be on the Login page. 3. User must be logged in the Assessor's Office portal 4. User must be on the request page of Certificate of Application | D20: 1. Search for the Assessor Office login page. 2. Log in using a registered email and password, and check the Terms & Conditions checkbox. 3. Click the Submit button. 4. Check the OTP verification sent to the registered email. 5. Enter the OTP in the verification field. 6. Click the New Request button. 7. Select Certificate of True Copy of Tax Declaration under Type of Certificate. 8. Select Transfer of Tax Declaration under Type of Certificate. 9. Choose the Personal option under Claiming. 10. Upload a valid .docx or .pdf file to the Proof of Ownership field. 11. Fill other required fields with valid files. 12. Click "Submit." | E20: These are the following details for the certification requirements. All fields are mandatory, and the system will not accept submission without uploading the required documents. Valid file types include .jpg, .png, .docx, or .pdf: Certification Requirements Note: All fields are mandatory. The system will not accept the submission if a document is not uploaded. Hover over the information icon to see the list of Valid IDs. (information icon) a) Contract of Lease jpg, png, docx or pdf files only File Upload File button b) Deed of Absolute Sale (DOAS) jpg, png, docx or pdf files only File Upload File button c) Proof of Ownership jpg, png, docx or pdf files only File Upload File button d) Contract to Sell jpg, png, docx or pdf files only File Upload File button Proof of Ownership field. • Accepts only valid file types: .jpg, .png, .docx, .pdf. | F20: PASSED
A21: =IF(B15<>"", "US-6-TC-" & TEXT(COUNTA($B$3:B21), "00"), "") -> US-6-TC-19 | B21: Verify that the system prevents form submission and displays a validation error when the Proof of Ownership upload field is left blank. | C21: 1. User must be on the Sta. Rosa Payroll Portal. 2. User must be on the Login page. 3. User must be logged in the Assessor's Office portal 4. User must be on the request page of Certificate of Application | D21: 1. Search for the Assessor Office login page. 2. Log in using a registered email and password, and check the Terms & Conditions checkbox. 3. Click the Submit button. 4. Check the OTP verification sent to the registered email. 5. Enter the OTP in the verification field. 6. Click the New Request button. 7. Select Certificate of True Copy of Tax Declaration under Type of Certificate. 8. Select Transfer of Tax Declaration under Type of Certificate. 9. Choose the Personal option under Claiming. 10. Leave the Proof of Ownership field blank. 11. Fill other required fields with valid files. 12. Click "Submit." | E21: These are the following details for the certification requirements. All fields are mandatory, and the system will not accept submission without uploading the required documents. Valid file types include .jpg, .png, .docx, or .pdf: Certification Requirements Note: All fields are mandatory. The system will not accept the submission if a document is not uploaded. Hover over the information icon to see the list of Valid IDs. (information icon) a) Contract of Lease jpg, png, docx or pdf files only File Upload File button b) Deed of Absolute Sale (DOAS) jpg, png, docx or pdf files only File Upload File button c) Proof of Ownership jpg, png, docx or pdf files only File Upload File button d) Contract to Sell jpg, png, docx or pdf files only File Upload File button Proof of Ownership field. • Blank uploads trigger a required field validation error, blocking submission "Please upload a Contract of Lease document in .jpg, .png, .docx, or .pdf format only." and blocks submission. | F21: PASSED
A22: =IF(B16<>"", "US-6-TC-" & TEXT(COUNTA($B$3:B22), "00"), "") -> US-6-TC-20 | B22: Verify that the system rejects and displays an error message when an unsupported file type is uploaded to the Proof of Ownership field. | F22: PASSED
A23: =IF(B16<>"", "US-6-TC-" & TEXT(COUNTA($B$3:B23), "00"), "") -> US-6-TC-21 | B23: Verify that the system accepts and successfully uploads a valid file (.jpg, .png, .docx, or .pdf) for the Contract to Sell field. | C23: 1. User must be on the Sta. Rosa Payroll Portal. 2. User must be on the Login page. 3. User must be logged in the Assessor's Office portal 4. User must be on the request page of Certificate of Application | D23: 1. Search for the Assessor Office login page. 2. Log in using a registered email and password, and check the Terms & Conditions checkbox. 3. Click the Submit button. 4. Check the OTP verification sent to the registered email. 5. Enter the OTP in the verification field. 6. Click the New Request button. 7. Select Certificate of True Copy of Tax Declaration under Type of Certificate. 8. Select Transfer of Tax Declaration under Type of Certificate. 9. Choose the Personal option under Claiming. 10. Upload a valid .jpg, .pdf, or .docx file to the Contract to Sell field. 11. Fill other required fields with valid files. 12. Click "Submit." | E23: These are the following details for the certification requirements. All fields are mandatory, and the system will not accept submission without uploading the required documents. Valid file types include .jpg, .png, .docx, or .pdf: Certification Requirements Note: All fields are mandatory. The system will not accept the submission if a document is not uploaded. Hover over the information icon to see the list of Valid IDs. (information icon) a) Contract of Lease jpg, png, docx or pdf files only File Upload File button b) Deed of Absolute Sale (DOAS) jpg, png, docx or pdf files only File Upload File button c) Proof of Ownership jpg, png, docx or pdf files only File Upload File button d) Contract to Sell jpg, png, docx or pdf files only File Upload File button Contract to Sell field: • Accepts only valid file types: .jpg, .png, .docx, .pdf. | F23: PASSED
A24: =IF(B17<>"", "US-6-TC-" & TEXT(COUNTA($B$3:B24), "00"), "") -> US-6-TC-22 | B24: Verify that the system prevents form submission and displays a validation error when the Contract to Sell upload field is left blank. | C24: 1. User must be on the Sta. Rosa Payroll Portal. 2. User must be on the Login page. 3. User must be logged in the Assessor's Office portal 4. User must be on the request page of Certificate of Application | D24: 1. Search for the Assessor Office login page. 2. Log in using a registered email and password, and check the Terms & Conditions checkbox. 3. Click the Submit button. 4. Check the OTP verification sent to the registered email. 5. Enter the OTP in the verification field. 6. Click the New Request button. 7. Select Certificate of True Copy of Tax Declaration under Type of Certificate. 8. Select Transfer of Tax Declaration under Type of Certificate. 9. Choose the Personal option under Claiming. 10. Leave the Contract to Sell field blank. 11. Fill other required fields with valid files. 12. Click "Submit." | E24: These are the following details for the certification requirements. All fields are mandatory, and the system will not accept submission without uploading the required documents. Valid file types include .jpg, .png, .docx, or .pdf: Certification Requirements Note: All fields are mandatory. The system will not accept the submission if a document is not uploaded. Hover over the information icon to see the list of Valid IDs. (information icon) a) Contract of Lease jpg, png, docx or pdf files only File Upload File button b) Deed of Absolute Sale (DOAS) jpg, png, docx or pdf files only File Upload File button c) Proof of Ownership jpg, png, docx or pdf files only File Upload File button d) Contract to Sell jpg, png, docx or pdf files only File Upload File button Contract to Sell field: • Blank uploads trigger a required field validation error, blocking submission "Please upload a Contract of Lease document in .jpg, .png, .docx, or .pdf format only." and blocks submission. | F24: PASSED
A25: =IF(B18<>"", "US-6-TC-" & TEXT(COUNTA($B$3:B25), "00"), "") -> US-6-TC-23 | B25: Verify that the system rejects and displays an error message when an unsupported file type is uploaded to the Contract to Sell field. | C25: 1. User must be on the Sta. Rosa Payroll Portal. 2. User must be on the Login page. 3. User must be logged in the Assessor's Office portal 4. User must be on the request page of Certificate of Application | D25: 1. Search for the Assessor Office login page. 2. Log in using a registered email and password, and check the Terms & Conditions checkbox. 3. Click the Submit button. 4. Check the OTP verification sent to the registered email. 5. Enter the OTP in the verification field. 6. Click the New Request button. 7. Select Certificate of True Copy of Tax Declaration under Type of Certificate. 8. Select Transfer of Tax Declaration under Type of Certificate. 9. Choose the Personal option under Claiming. 10. Upload a .exe or .zip (invalidfile) to the Contract to Sell field. 11. Fill other required fields with valid files. 12. Click "Submit." | E25: These are the following details for the certification requirements. All fields are mandatory, and the system will not accept submission without uploading the required documents. Valid file types include .jpg, .png, .docx, or .pdf: Certification Requirements Note: All fields are mandatory. The system will not accept the submission if a document is not uploaded. Hover over the information icon to see the list of Valid IDs. (information icon) a) Contract of Lease jpg, png, docx or pdf files only File Upload File button b) Deed of Absolute Sale (DOAS) jpg, png, docx or pdf files only File Upload File button c) Proof of Ownership jpg, png, docx or pdf files only File Upload File button d) Contract to Sell jpg, png, docx or pdf files only File Upload File button Contract to Sell field: • Uploading an invalid file type (e.g., .exe, .zip) triggers a clear validation error message "Please upload a Contract of Lease document in .jpg, .png, .docx, or .pdf format only." and blocks submission. | F25: PASSED
A26: =IF(B19<>"", "US-6-TC-" & TEXT(COUNTA($B$3:B26), "00"), "") -> US-6-TC-24 | B26: Verify that selecting “Yes” for “Are you a Company/Bank Developer?” displays the "Secretary’s Certificate and one (1) employee ID" | C26: 1. User must be on the Sta. Rosa Payroll Portal. 2. User must be on the Login page. 3. User must be logged in the Assessor's Office portal 4. User must be on the request page of Certificate of Application | D26: 1. Search for the Assessor Office login page. 2. Log in using a registered email and password, and check the Terms & Conditions checkbox. 3. Click the Submit button. 4. Check the OTP verification sent to the registered email. 5. Enter the OTP in the verification field. 6. Click the New Request button. 7. Select Certificate of True Copy of Tax Declaration under Type of Certificate. 8. Select Transfer of Tax Declaration under Type of Certificate. 9. Choose the Personal option under Claiming. 10. Upload a valid file (.jpg, .png, .docx, or .pdf) to the following fields: • Contract of Lease • Deed of Absolute Sale (DOAS) • Proof of Ownership • Contract to Sell 11. Select Yes for “Are you a Company/Bank Developer?” 12. Click the Upload button for: • Secretary’s Certificate • Employee ID 13. Fill out all other required fields 14. Click the Submit button. | E26: When the user selects “Yes” for the question “Are you a Company/Bank Developer?”, the system should: A new section labeled “Secretary’s Certificate and one (1) employee ID” should appear immediately without requiring a page refresh or redirection. Each upload field must contain: • A File label identifying the required document. • A note under or beside each field: "jpg, png, docx or pdf files only" • A button or area labeled “Upload File” to upload the supported file. | F26: PASSED
A27: =IF(B20<>"", "US-6-TC-" & TEXT(COUNTA($B$3:B27), "00"), "") -> US-6-TC-25 | B27: Verify that the user is able to upload files (e.g., .jpg, .png, .docx, or .pdf only) for the "Photocopy of Loan Agreement" field. | C27: 1. User must be on the Sta. Rosa Payroll Portal. 2. User must be on the Login page. 3. User must be logged in the Assessor's Office portal 4. User must be on the request page of Certificate of Application | D27: 1. Search for the Assessor Office login page. 2. Log in using a registered email and password, and check the Terms & Conditions checkbox. 3. Click the Submit button. 4. Check the OTP verification sent to the registered email. 5. Enter the OTP in the verification field. 6. Click the New Request button. 7. Select Certificate of True Copy of Tax Declaration under Type of Certificate. 8. Select Transfer of Tax Declaration under Type of Certificate. 9. Choose the Personal option under Claiming. 10. Upload a valid file (.jpg, .png, .docx, or .pdf) to the following fields: • Contract of Lease • Deed of Absolute Sale (DOAS) • Proof of Ownership • Contract to Sell 11. Select Yes for “Are you a Company/Bank Developer?” 12. Click the Upload button for: • Secretary’s Certificate • Employee ID 13. Fill out all other required fields 14. Click the Submit button. | E27: When the user selects “Yes” for the question “Are you a Company/Bank Developer?”, the system should: A new section labeled “Secretary’s Certificate and one (1) employee ID” should appear immediately without requiring a page refresh or redirection. Each upload field must contain: • A File label identifying the required document. • A note under or beside each field: "jpg, png, docx or pdf files only" • A button or area labeled “Upload File” to upload the supported file. | F27: PASSED
A28: =IF(B21<>"", "US-6-TC-" & TEXT(COUNTA($B$3:B28), "00"), "") -> US-6-TC-26 | B28: Verify that the form prevents submission when “Are you a Company/Bank Developer?” is Yes but "Secretary’s Certificate and one (1) employee ID" files are not uploaded. | C28: 1. User must be on the Sta. Rosa Payroll Portal. 2. User must be on the Login page. 3. User must be logged in the Assessor's Office portal 4. User must be on the request page of Certificate of Application | D28: 1. Search for the Assessor Office login page. 2. Log in using a registered email and password, and check the Terms & Conditions checkbox. 3. Click the Submit button. 4. Check the OTP verification sent to the registered email. 5. Enter the OTP in the verification field. 6. Click the New Request button. 7. Select Certificate of True Copy of Tax Declaration under Type of Certificate. 8. Select Transfer of Tax Declaration under Type of Certificate. 9. Choose the Personal option under Claiming. 10. Upload a valid file (.jpg, .png, .docx, or .pdf) to the following fields: • Contract of Lease • Deed of Absolute Sale (DOAS) • Proof of Ownership • Contract to Sell 11. Select Yes for “Are you a Company/Bank Developer?” 12. Do not upload any files to: • Secretary’s Certificate • Employee ID 13. Fill out all other required fields. 14. Click Submit. | E28: When the user selects "Yes" for the "Are you a Company/Bank Developer?" question and does not upload the required files under the "Secretary’s Certificate and one (1) employee ID" section: A new section labeled “Secretary’s Certificate and one (1) employee ID” should immediately appear on the form without requiring a page reload. Each upload field must contain: • A File label identifying the required document. • A note under or beside each field: "jpg, png, docx or pdf files only" • A button or area labeled “Upload File” to upload the supported file. Upon clicking Submit, the system should detect that the Secretary’s Certificate and/or Employee ID files have not been uploaded. The form submission must be blocked. A clear and specific error message should be displayed near each empty file upload field, such as: “Please upload the Secretary’s Certificate and Employee ID.” | F28: PASSED
A29: =IF(B23<>"", "US-6-TC-" & TEXT(COUNTA($B$3:B29), "00"), "") -> US-6-TC-27 | B29: Verify that the system rejects unsupported file types for “Are you a Company/Bank Developer?” under "Secretary’s Certificate and one (1) employee ID" uploads. | C29: 1. User must be on the Sta. Rosa Payroll Portal. 2. User must be on the Login page. 3. User must be logged in the Assessor's Office portal 4. User must be on the request page of Certificate of Application | D29: 1. Search for the Assessor Office login page. 2. Log in using a registered email and password, and check the Terms & Conditions checkbox. 3. Click the Submit button. 4. Check the OTP verification sent to the registered email. 5. Enter the OTP in the verification field. 6. Click the New Request button. 7. Select Certificate of True Copy of Tax Declaration under Type of Certificate. 8. Select Transfer of Tax Declaration under Type of Certificate. 9. Choose the Personal option under Claiming. 10. Upload a valid file (.jpg, .png, .docx, or .pdf) to the following fields: • Contract of Lease • Deed of Absolute Sale (DOAS) • Proof of Ownership • Contract to Sell 11. Select Yes for “Are you a Company/Bank Developer?” 12. Upload unsupported file types (e.g., .exe, .zip, .js) to: • Secretary’s Certificate • Employee ID 13. Complete other required fields. 14. Click Submit. | E29: When the user selects "Yes" for the "Are you a Company/Bank Developer?" question and does not upload the required files under the "Secretary’s Certificate and one (1) employee ID" section: A new section labeled “Secretary’s Certificate and one (1) employee ID” should immediately appear on the form without requiring a page reload. Each upload field must contain: • A File label identifying the required document. • A note under or beside each field: "jpg, png, docx or pdf files only" • A button or area labeled “Upload File” to upload the supported file. If the user tries to upload an unsupported file format (e.g., .exe, .txt, .zip), an immediate inline warning should appear: • The file must be rejected and not attached to the form. | F29: PASSED
A30: =IF(B24<>"", "US-6-TC-" & TEXT(COUNTA($B$3:B30), "00"), "") -> US-6-TC-28 | B30: Verify that the user is able to select “No” for “Are you a Company/Bank Developer?” | C30: 1. User must be on the Sta. Rosa Payroll Portal. 2. User must be on the Login page. 3. User must be logged in the Assessor's Office portal 4. User must be on the request page of Certificate of Application | D30: 1. Search for the Assessor Office login page. 2. Log in using a registered email and password, and check the Terms & Conditions checkbox. 3. Click the Submit button. 4. Check the OTP verification sent to the registered email. 5. Enter the OTP in the verification field. 6. Click the New Request button. 7. Select Certificate of True Copy of Tax Declaration under Type of Certificate. 8. Select Transfer of Tax Declaration under Type of Certificate. 9. Choose the Personal option under Claiming. 10. Upload a valid file (.jpg, .png, .docx, or .pdf) to the following fields: • Contract of Lease • Deed of Absolute Sale (DOAS) • Proof of Ownership • Contract to Sell 11. Select No for “Are you a Company/Bank Developer?” 12. Fill out all remaining required fields. 13. Click Submit. | E30: When the user clicks or selects the “No” option for the question “Are you a Company/Bank Developer?”: • The system should register the selection without delay or requiring a page reload. • The selection should be visually confirmed (e.g., radio button becomes filled or highlighted). • The “Secretary’s Certificate and one (1) employee ID” section should not appear at all if it hasn't already been shown. | F30: PASSED
A31: =IF(B25<>"", "US-6-TC-" & TEXT(COUNTA($B$3:B31), "00"), "") -> US-6-TC-29 | B31: Verify that selecting “Yes” for “Is this a Loan Mortgage?” displays the "Photocopy of Loan Agreement" upload field. | C31: 1. User must be on the Sta. Rosa Payroll Portal. 2. User must be on the Login page. 3. User must be logged in the Assessor's Office portal 4. User must be on the request page of Certificate of Application | D31: 1. Search for the Assessor Office login page. 2. Log in using a registered email and password, and check the Terms & Conditions checkbox. 3. Click the Submit button. 4. Check the OTP verification sent to the registered email. 5. Enter the OTP in the verification field. 6. Click the New Request button. 7. Select Certificate of True Copy of Tax Declaration under Type of Certificate. 8. Select Transfer of Tax Declaration under Type of Certificate. 9. Choose the Personal option under Claiming. 10. Upload a valid file (.jpg, .png, .docx, or .pdf) to the following fields: • Contract of Lease • Deed of Absolute Sale (DOAS) • Proof of Ownership • Contract to Sell 11. Select Yes for “Are you a Company/Bank Developer?” 12. On the upload button for "Secretary’s Certificate and one (1) employee ID", the user must upload files for both: • Secretary’s Certificate • Employee ID 13. Select Yes for “Is this a Loan Mortgage?" 14. On the upload button for "Photocopy of Loan Agreement", the user must upload a valid file to proceed with the form submission. 15. Fill out all other required fields 16. Click the Submit button. | E31: When the user selects “Yes” for the question “Is this a Loan Mortgage?”, the system should: A new section labeled “Photocopy of Loan Agreement” should appear immediately without requiring a page refresh or redirection. Each upload field must contain: • A File label identifying the required document. • A note under or beside each field: "jpg, png, docx or pdf files only" • A button or area labeled “Upload File” to upload the supported file. | F31: PASSED
A32: =IF(B26<>"", "US-6-TC-" & TEXT(COUNTA($B$3:B32), "00"), "") -> US-6-TC-30 | B32: Verify that the user is able to upload only valid file types (.jpg, .png, .docx, or .pdf) in the "Photocopy of Loan Agreement" field. | C32: 1. User must be on the Sta. Rosa Payroll Portal. 2. User must be on the Login page. 3. User must be logged in the Assessor's Office portal 4. User must be on the request page of Certificate of Application | D32: 1. Search for the Assessor Office login page. 2. Log in using a registered email and password, and check the Terms & Conditions checkbox. 3. Click the Submit button. 4. Check the OTP verification sent to the registered email. 5. Enter the OTP in the verification field. 6. Click the New Request button. 7. Select Certificate of True Copy of Tax Declaration under Type of Certificate. 8. Select Transfer of Tax Declaration under Type of Certificate. 9. Choose the Personal option under Claiming. 10. Upload a valid file (.jpg, .png, .docx, or .pdf) to the following fields: • Contract of Lease • Deed of Absolute Sale (DOAS) • Proof of Ownership • Contract to Sell 11. Select Yes for “Are you a Company/Bank Developer?” 12. On the upload button for "Secretary’s Certificate and one (1) employee ID", the user must upload files for both: • Secretary’s Certificate • Employee ID 13. Select Yes for “Is this a Loan Mortgage?" 14. On the upload button for "Photocopy of Loan Agreement", the user must upload a valid file to proceed with the form submission. 15. Fill out all other required fields 16. Click the Submit button. | E32: When the user selects “Yes” for the question “Is this a Loan Mortgage?”, the system should: A new section labeled “Photocopy of Loan Agreement” should appear immediately without requiring a page refresh or redirection. Each upload field must contain: • A File label identifying the required document. • A note under or beside each field: "jpg, png, docx or pdf files only" • A button or area labeled “Upload File” to upload the supported file. | F32: PASSED
